// converted by version  [v3.0.4]
// on Sun Aug 09 13:28:59 SGT 2020

.package thetapass {
	.aid 0x54:0x50:0x41:0x53:0x53;
	.version 1.0;

	.imports {
		0xA0:0x0:0x0:0x0:0x62:0x0:0x1 1.0;		//java/lang
		0xA0:0x0:0x0:0x0:0x62:0x1:0x1 1.5;		//javacard/framework
		0xA0:0x0:0x0:0x0:0x62:0x1:0x2 1.5;		//javacard/security
		0x4B:0x4D:0x31:0x30:0x31 1.0;		//KM101
		0xA0:0x0:0x0:0x0:0x62:0x2:0x1 1.5;		//javacardx/crypto
	}

	.applet {
		0x54:0x50:0x41:0x53:0x53:0x1:0x0 ThetaPassApplet;
	}

	.constantPool {
		// 0
		instanceFieldRef byte[] APIShim/nonceBuffer;
		// 1
		instanceFieldRef short APIShim/aocPinMaxRetry;
		// 2
		instanceFieldRef byte[] APIShim/tempBuf;
		// 3
		instanceFieldRef byte[] APIShim/aocPin;
		// 4
		instanceFieldRef 1.6 ThetaPassApplet/apiAID;
		// 5
		instanceFieldRef 4.1 ThetaPassApplet/cipher;
		// 6
		instanceFieldRef 4.1 ThetaPassApplet/cipherNoPad;
		// 7
		instanceFieldRef 2.22 ThetaPassApplet/ecdh;
		// 8
		instanceFieldRef 2.11 ThetaPassApplet/md;
		// 9
		instanceFieldRef byte[] ThetaPassApplet/defaultPin;
		// 10
		instanceFieldRef 2.20 ThetaPassApplet/sessKey;
		// 11
		instanceFieldRef byte[] ThetaPassApplet/b0;
		// 12
		instanceFieldRef byte[] ThetaPassApplet/b1;
		// 13
		instanceFieldRef byte[] ThetaPassApplet/b2;
		// 14
		instanceFieldRef short[] ThetaPassApplet/sb;
		// 15
		instanceFieldRef byte[] ThetaPassApplet/fs;
		// 16
		instanceFieldRef byte[] ThetaPassApplet/fsIV;
		// 17
		instanceFieldRef 1.9 ThetaPassApplet/pin;
		// 18
		instanceFieldRef 2.20 ThetaPassApplet/fsKey;
		// 19
		instanceFieldRef 2.18 ThetaPassApplet/privKey;
		// 20
		instanceFieldRef 2.19 ThetaPassApplet/pubKey;
		// 21
		instanceFieldRef 2.16 ThetaPassApplet/kp;
		// 22
		staticFieldRef byte[] APIShim/TXT_FAILED;
		// 23
		staticFieldRef byte[] APIShim/TXT_CANCELLED;
		// 24
		staticFieldRef byte[] APIShim/TXT_CRED_MENU_LIST;
		// 25
		staticFieldRef byte[] APIShim/BCD_SIZE_PER_BYTES;
		// 26
		staticFieldRef byte[] Codec/BCD_SIZE_PER_BYTES;
		// 27
		staticFieldRef byte[] ECC/EC_P256R1_FIELD_A;
		// 28
		.classRef 2.17;		// javacard/security/ECKey
		// 29
		staticFieldRef byte[] ECC/EC_P256R1_FIELD_B;
		// 30
		staticFieldRef byte[] ECC/EC_P256R1_FP;
		// 31
		staticFieldRef byte[] ECC/EC_P256R1_FIELD_G;
		// 32
		staticFieldRef byte[] ECC/EC_P256R1_FIELD_R;
		// 33
		staticMethodRef 1.16.0([BS[BSS)B;		// javacard/framework/Util.arrayCompare([BS[BSS)B
		// 34
		.classRef 0.2;		// java/lang/Exception
		// 35
		staticFieldRef byte[] ThetaPassApplet/serverAID;
		// 36
		staticMethodRef 1.8.11([BSB)Ljavacard/framework/AID;;		// javacard/framework/JCSystem.lookupAID([BSB)Ljavacard/framework/AID;
			.descriptor	Ljavacard/framework/AID;	1.6;

		// 37
		staticMethodRef 0.0.0()V;		// java/lang/Object.<init>()V
		// 38
		staticMethodRef 1.8.4(Ljavacard/framework/AID;B)Ljavacard/framework/Shareable;;		// javacard/framework/JCSystem.getAppletShareableInterfaceObject(Ljavacard/framework/AID;B)Ljavacard/framework/Shareable;
			.descriptor	Ljavacard/framework/AID;	1.6;
			.descriptor	Ljavacard/framework/Shareable;	1.2;

		// 39
		.classRef APIShim;
		// 40
		staticMethodRef APIShim/<init>()V;
		// 41
		staticFieldRef APIShim ThetaPassApplet/apishim;
		// 42
		virtualMethodRef APIShim/initEnv([B)Z;
		// 43
		.classRef ThetaPassApplet;
		// 44
		staticMethodRef ThetaPassApplet/<init>()V;
		// 45
		staticMethodRef 1.3.0()V;		// javacard/framework/Applet.<init>()V
		// 46
		staticMethodRef 1.8.13(SB)[B;		// javacard/framework/JCSystem.makeTransientByteArray(SB)[B
		// 47
		staticMethodRef APIShim/generateRandomAOCPin([BSS)V;
		// 48
		staticFieldRef 2.14 ThetaPassApplet/randomData;
		// 49
		virtualMethodRef 2.14.1([BSS)V;		// generateData([BSS)V
		// 50
		staticMethodRef 1.16.3([BSSB)S;		// javacard/framework/Util.arrayFillNonAtomic([BSSB)S
		// 51
		staticMethodRef 1.16.2([BS[BSS)S;		// javacard/framework/Util.arrayCopyNonAtomic([BS[BSS)S
		// 52
		staticFieldRef byte[] APIShim/appName;
		// 53
		staticFieldRef byte[] APIShim/defaultExpiryTime;
		// 54
		staticFieldRef 3.1 ThetaPassApplet/api;
		// 55
		staticMethodRef 1.8.15(SB)[S;		// javacard/framework/JCSystem.makeTransientShortArray(SB)[S
		// 56
		.classRef 3.1;		// KM101/T101OpenAPI
		// 57
		virtualMethodRef APIShim/finalizeContainer([BSS[B)Z;
		// 58
		virtualMethodRef APIShim/enableFPAccess([BSS[B)Z;
		// 59
		staticMethodRef 2.14.0(B)Ljavacard/security/RandomData;;		// javacard/security/RandomData.getInstance(B)Ljavacard/security/RandomData;
			.descriptor	Ljavacard/security/RandomData;	2.14;

		// 60
		staticMethodRef 4.1.0(BZ)Ljavacardx/crypto/Cipher;;		// javacardx/crypto/Cipher.getInstance(BZ)Ljavacardx/crypto/Cipher;
			.descriptor	Ljavacardx/crypto/Cipher;	4.1;

		// 61
		staticMethodRef 2.11.0(BZ)Ljavacard/security/MessageDigest;;		// javacard/security/MessageDigest.getInstance(BZ)Ljavacard/security/MessageDigest;
			.descriptor	Ljavacard/security/MessageDigest;	2.11;

		// 62
		.classRef 1.9;		// javacard/framework/OwnerPIN
		// 63
		staticMethodRef 1.9.0(BB)V;		// javacard/framework/OwnerPIN.<init>(BB)V
		// 64
		staticMethodRef 1.16.5(BB)S;		// javacard/framework/Util.makeShort(BB)S
		// 65
		virtualMethodRef 1.9.8([BSB)V;		// update([BSB)V
		// 66
		staticMethodRef 2.13.0(BSZ)Ljavacard/security/Key;;		// javacard/security/KeyBuilder.buildKey(BSZ)Ljavacard/security/Key;
			.descriptor	Ljavacard/security/Key;	2.0;

		// 67
		.classRef 2.20;		// javacard/security/AESKey
		// 68
		staticMethodRef 1.7.1(S)V;		// javacard/framework/ISOException.throwIt(S)V
		// 69
		.classRef 2.18;		// javacard/security/ECPrivateKey
		// 70
		virtualMethodRef APIShim/authContainer([BSS[BS[B)S;
		// 71
		.classRef 2.19;		// javacard/security/ECPublicKey
		// 72
		virtualMethodRef APIShim/uxRender(BBBBB[BSS[BSS[BSS[B)S;
		// 73
		staticMethodRef ECC/setCurveParameters(Ljavacard/security/ECKey;)V;
			.descriptor	Ljavacard/security/ECKey;	2.17;

		// 74
		.classRef 2.16;		// javacard/security/KeyPair
		// 75
		staticMethodRef 2.16.1(Ljavacard/security/PublicKey;Ljavacard/security/PrivateKey;)V;		// javacard/security/KeyPair.<init>(Ljavacard/security/PublicKey;Ljavacard/security/PrivateKey;)V
			.descriptor	Ljavacard/security/PublicKey;	2.3;
			.descriptor	Ljavacard/security/PrivateKey;	2.2;

		// 76
		staticFieldRef byte[] APIShim/TXT_SUCCESS;
		// 77
		virtualMethodRef 2.16.1()V;		// genKeyPair()V
		// 78
		staticMethodRef 2.22.0(BZ)Ljavacard/security/KeyAgreement;;		// javacard/security/KeyAgreement.getInstance(BZ)Ljavacard/security/KeyAgreement;
			.descriptor	Ljavacard/security/KeyAgreement;	2.22;

		// 79
		virtualMethodRef 1.3.1()V;		// register()V
		// 80
		virtualMethodRef APIShim/mainMenuUI([B)S;
		// 81
		staticMethodRef ThetaPassApplet/listRecordLocIndexWithType(B[BS)S;
		// 82
		staticFieldRef short[] APIShim/MENU_LIST_TITLE_OFF;
		// 83
		staticFieldRef short[] APIShim/MENU_LIST_TITLE_LEN;
		// 84
		virtualMethodRef APIShim/showScrollingList([BSSS[BSS[B)S;
		// 85
		staticMethodRef ThetaPassApplet/getRecordLocOffset(S)S;
		// 86
		staticMethodRef ThetaPassApplet/getEName1FromLocOff(S[BS)S;
		// 87
		virtualMethodRef APIShim/confirmationUI([BSS[BSS[B)Z;
		// 88
		staticMethodRef ThetaPassApplet/cryptoContent(BS[BS[BS)Z;
		// 89
		staticMethodRef ThetaPassApplet/getEName0FromLocOff(S[BS)S;
		// 90
		virtualMethodRef 1.10.6()S;		// setIncomingAndReceive()S
		// 91
		virtualMethodRef 2.11.4()V;		// reset()V
		// 92
		virtualMethodRef 2.11.5([BSS)V;		// update([BSS)V
		// 93
		virtualMethodRef 2.11.1([BSS[BS)S;		// doFinal([BSS[BS)S
		// 94
		virtualMethodRef 2.22.1(Ljavacard/security/PrivateKey;)V;		// init(Ljavacard/security/PrivateKey;)V
			.descriptor	Ljavacard/security/PrivateKey;	2.2;

		// 95
		virtualMethodRef 2.22.3([BSS[BS)S;		// generateSecret([BSS[BS)S
		// 96
		staticMethodRef Codec/intToBytes(I[BS)V;
		// 97
		staticMethodRef Codec/toDecimalASCII([BSS[BS)S;
		// 98
		staticFieldRef byte[] APIShim/TXT_CCODE;
		// 99
		staticFieldRef byte[] APIShim/TXT_PROMPT_OKC;
		// 100
		staticFieldRef byte[] APIShim/TXT_SECURE_SESS;
		// 101
		virtualMethodRef 4.1.4(Ljavacard/security/Key;B[BSS)V;		// init(Ljavacard/security/Key;B[BSS)V
			.descriptor	Ljavacard/security/Key;	2.0;

		// 102
		virtualMethodRef 4.1.1([BSS[BS)S;		// doFinal([BSS[BS)S
		// 103
		staticMethodRef Codec/shortToBytes(S[BS)V;
		// 104
		staticMethodRef ThetaPassApplet/countFreeRecords()S;
		// 105
		staticMethodRef 1.16.6([BSS)S;		// javacard/framework/Util.setShort([BSS)S
		// 106
		staticMethodRef ThetaPassApplet/countTotalRecords()S;
		// 107
		virtualMethodRef 1.10.8(SS)V;		// setOutgoingAndSend(SS)V
		// 108
		staticMethodRef ThetaPassApplet/countRecordByType(B)S;
		// 109
		staticMethodRef ThetaPassApplet/getRecordEName0List(BSS[BS)S;
		// 110
		virtualMethodRef 1.10.16()S;		// getOffsetCdata()S
		// 111
		staticMethodRef ThetaPassApplet/searchRecordLocWithEName0AndType(B[BSS)S;
		// 112
		staticMethodRef Codec/isInputAllowable([BSSZ)Z;
		// 113
		staticMethodRef ThetaPassApplet/setRecord(B[BSS[BSS[BSS[BS)Z;
		// 114
		staticMethodRef ThetaPassApplet/isAuthNeededFromFlag(B)Z;
		// 115
		staticMethodRef ThetaPassApplet/getTypeFromFlag(B)B;
		// 116
		staticMethodRef ThetaPassApplet/searchRecordLocOffsetWithEName0AndType(B[BSS)S;
		// 117
		staticMethodRef 1.8.1()V;		// javacard/framework/JCSystem.beginTransaction()V
		// 118
		staticMethodRef 1.8.2()V;		// javacard/framework/JCSystem.commitTransaction()V
		// 119
		staticMethodRef ThetaPassApplet/getEmptyRecordLoc()S;
		// 120
		staticMethodRef 1.16.1([BS[BSS)S;		// javacard/framework/Util.arrayCopy([BS[BSS)S
		// 121
		virtualMethodRef 1.3.3()Z;		// selectingApplet()Z
		// 122
		virtualMethodRef 1.10.1()[B;		// getBuffer()[B
		// 123
		staticMethodRef ThetaPassApplet/initAPI([B)V;
		// 124
		staticMethodRef ThetaPassApplet/fsGet(Ljavacard/framework/APDU;[B)V;
			.descriptor	Ljavacard/framework/APDU;	1.10;

		// 125
		staticMethodRef ThetaPassApplet/fsPut(Ljavacard/framework/APDU;[B)V;
			.descriptor	Ljavacard/framework/APDU;	1.10;

		// 126
		staticMethodRef ThetaPassApplet/mainMenu(Ljavacard/framework/APDU;[B)V;
			.descriptor	Ljavacard/framework/APDU;	1.10;

		// 127
		staticMethodRef ThetaPassApplet/secureChannel(Ljavacard/framework/APDU;[B)V;
			.descriptor	Ljavacard/framework/APDU;	1.10;

	}

	.class public APIShim 0 extends 0.0 {		// extends java/lang/Object

		.fields {
			private byte[] aocPin 0;		// [B
			private byte[] nonceBuffer 1;		// [B
			private byte[] tempBuf 2;		// [B
			private short aocPinMaxRetry 3;		// S
			public static final byte[] appName 0 = {84,72,69,84,65,80,65,83,83};		// [B
			public static final byte[] defaultExpiryTime 1 = {0,0,0,0};		// [B
			public static final byte[] TXT_CCODE 2 = {79,84,80,32,67,111,100,101};		// [B
			public static final byte[] TXT_PROMPT_OKC 3 = {80,114,101,115,115,32,79,75,47,67};		// [B
			public static final byte[] TXT_SECURE_SESS 4 = {83,69,67,32,83,69,83,83,78};		// [B
			public static final byte[] TXT_SUCCESS 5 = {32,32,32,79,112,101,114,97,116,105,111,110,32,32,32,32,32,32,32,32,83,117,99,99,101,115,115};		// [B
			public static final byte[] TXT_FAILED 6 = {32,32,32,79,112,101,114,97,116,105,111,110,32,32,32,32,32,32,32,32,70,97,105,108,101,100};		// [B
			public static final byte[] TXT_CANCELLED 7 = {32,32,32,79,112,101,114,97,116,105,111,110,32,32,32,32,32,32,32,67,97,97,110,99,101,108,108,101,100};		// [B
			public static final byte[] BCD_SIZE_PER_BYTES 8 = {0,3,5,8,10,13,15,17,20,22,25,27,29,32,34,37,39,41,44,46,49,51,53,56,58,61,63,66,68,70,73,75,78};		// [B
			public static final byte[] TXT_CRED_MENU_LIST 9 = {14,80,73,78,32,38,32,80,65,83,83,87,79,82,68,9,79,84,80,32,67,79,68,69,83,8,81,82,32,67,79,68,69,83,8,78,79,84,69,66,79,79,75,9,79,82,71,65,78,73,90,69,82};		// [B
			public static final short[] MENU_LIST_TITLE_OFF 10 = {1,16,26,35,44};		// [S
			public static final short[] MENU_LIST_TITLE_LEN 11 = {3,3,2,8,9};		// [S
		}

		.publicMethodTable 1 {
			equals(Ljava/lang/Object;)Z;
			initEnv([B)Z;
			enableFPAccess([BSS[B)Z;
			destroyEnv()Z;
			authContainer([BSS[BS[B)S;
			finalizeContainer([BSS[B)Z;
			confirmationUI([BSS[BSS[B)Z;
			opsStatusUI(Z[BSS[B)V;
			opsCancelStatusUI([BSS[B)V;
			pinInputUI([BSS[BSS[B)S;
			mainMenuUI([B)S;
			showMenuKeyQR([B[B)S;
			showScrollingList([BSSS[BSS[B)S;
			uxRender(BBBBB[BSS[BSS[BSS[B)S;
		}

		.packageMethodTable 0 {
		}

		.method public <init>()V 0 {
			.stack 4;
			.locals 0;

				L0:	aload_0;
					invokespecial 37;		// java/lang/Object.<init>()V
					aload_0;
					bspush 8;
					sconst_1;
					invokestatic 46;		// javacard/framework/JCSystem.makeTransientByteArray(SB)[B
					putfield_a 0;		// reference thetapass/APIShim.nonceBuffer
					aload_0;
					sconst_5;
					putfield_s 1;		// short thetapass/APIShim.aocPinMaxRetry
					aload_0;
					aconst_null;
					putfield_a 2;		// reference thetapass/APIShim.tempBuf
					aload_0;
					bspush 8;
					newarray 11;
					putfield_a 3;		// reference thetapass/APIShim.aocPin
					aload_0;
					getfield_a_this 3;		// reference thetapass/APIShim.aocPin
					sconst_0;
					getfield_a_this 3;		// reference thetapass/APIShim.aocPin
					arraylength;
					invokespecial 47;		// thetapass/APIShim.generateRandomAOCPin([BSS)V
					return;
		}

		.method private generateRandomAOCPin([BSS)V {
			.stack 4;
			.locals 1;

				L0:	getstatic_a 48;		// reference thetapass/ThetaPassApplet.randomData
					getfield_a_this 0;		// reference thetapass/APIShim.nonceBuffer
					sconst_0;
					sload_3;
					invokevirtual 49;		// generateData([BSS)V
					sconst_0;
					sstore 4;
				L1:	goto L3;
				L2:	aload_1;
					sload 4;
					sload_2;
					sadd;
					getfield_a_this 0;		// reference thetapass/APIShim.nonceBuffer
					sload 4;
					baload;
					bspush 15;
					sand;
					bspush 10;
					srem;
					sspush 255;
					sand;
					bspush 48;
					sor;
					s2b;
					bastore;
					sinc 4 1;
				L3:	sload 4;
					sload_3;
					if_scmplt L2;
				L4:	return;
		}

		.method public initEnv([B)Z 1 {
			.stack 12;
			.locals 1;

				L0:	sconst_0;
					sstore_2;
				L1:	aload_1;
					sconst_0;
					sspush 256;
					sconst_0;
					invokestatic 50;		// javacard/framework/Util.arrayFillNonAtomic([BSSB)S
					pop;
					aload_1;
					sconst_0;
					bspush -128;
					bastore;
					getfield_a_this 3;		// reference thetapass/APIShim.aocPin
					sconst_0;
					aload_1;
					sconst_1;
					getfield_a_this 3;		// reference thetapass/APIShim.aocPin
					arraylength;
					invokestatic 51;		// javacard/framework/Util.arrayCopyNonAtomic([BS[BSS)S
					pop;
					getstatic_a 52;		// reference thetapass/APIShim.appName
					sconst_0;
					aload_1;
					sconst_1;
					getfield_a_this 3;		// reference thetapass/APIShim.aocPin
					arraylength;
					sadd;
					getstatic_a 52;		// reference thetapass/APIShim.appName
					arraylength;
					invokestatic 51;		// javacard/framework/Util.arrayCopyNonAtomic([BS[BSS)S
					pop;
					getstatic_a 53;		// reference thetapass/APIShim.defaultExpiryTime
					sconst_0;
					aload_1;
					sconst_1;
					getfield_a_this 3;		// reference thetapass/APIShim.aocPin
					arraylength;
					sadd;
					getstatic_a 52;		// reference thetapass/APIShim.appName
					arraylength;
					sadd;
					sconst_4;
					invokestatic 51;		// javacard/framework/Util.arrayCopyNonAtomic([BS[BSS)S
					pop;
					getstatic_a 54;		// reference thetapass/ThetaPassApplet.api
					aload_1;
					sconst_0;
					baload;
					aload_1;
					sconst_1;
					getfield_a_this 3;		// reference thetapass/APIShim.aocPin
					arraylength;
					getfield_s_this 1;		// short thetapass/APIShim.aocPinMaxRetry
					aload_1;
					sconst_1;
					getfield_a_this 3;		// reference thetapass/APIShim.aocPin
					arraylength;
					sadd;
					getstatic_a 52;		// reference thetapass/APIShim.appName
					arraylength;
					aload_1;
					sconst_1;
					getfield_a_this 3;		// reference thetapass/APIShim.aocPin
					arraylength;
					sadd;
					getstatic_a 52;		// reference thetapass/APIShim.appName
					arraylength;
					sadd;
					invokeinterface 11 56 0;		// KM101/T101OpenAPI
					sstore_2;
					sload_2;
					ifeq L3;
				L2:	aload_0;
					getfield_a_this 3;		// reference thetapass/APIShim.aocPin
					sconst_0;
					getfield_a_this 3;		// reference thetapass/APIShim.aocPin
					arraylength;
					aload_1;
					invokevirtual 57;		// finalizeContainer([BSS[B)Z
					sstore_2;
				L3:	sload_2;
					ifeq L5;
				L4:	aload_0;
					getfield_a_this 3;		// reference thetapass/APIShim.aocPin
					sconst_0;
					getfield_a_this 3;		// reference thetapass/APIShim.aocPin
					arraylength;
					aload_1;
					invokevirtual 58;		// enableFPAccess([BSS[B)Z
					sstore_2;
					goto L6;
				L5:	bspush 111;
					bspush -93;
					invokestatic 64;		// javacard/framework/Util.makeShort(BB)S
					invokestatic 68;		// javacard/framework/ISOException.throwIt(S)V
				L6:	sload_2;
					sreturn;
		}

		.method public enableFPAccess([BSS[B)Z 2 {
			.stack 7;
			.locals 0;

				L0:	aload 4;
					sconst_0;
					bspush 6;
					bastore;
					aload 4;
					sconst_1;
					sconst_1;
					bastore;
					getstatic_a 54;		// reference thetapass/ThetaPassApplet.api
					aload 4;
					sconst_0;
					baload;
					aload 4;
					sconst_1;
					sconst_1;
					aload 4;
					sconst_2;
					invokeinterface 7 56 3;		// KM101/T101OpenAPI
					ifeq L4;
				L1:	aload 4;
					sconst_2;
					getfield_a_this 0;		// reference thetapass/APIShim.nonceBuffer
					sconst_0;
					bspush 8;
					invokestatic 51;		// javacard/framework/Util.arrayCopyNonAtomic([BS[BSS)S
					pop;
					aload_0;
					aload_1;
					sload_2;
					sload_3;
					getfield_a_this 0;		// reference thetapass/APIShim.nonceBuffer
					sconst_0;
					aload 4;
					invokevirtual 70;		// authContainer([BSS[BS[B)S
					sconst_1;
					if_scmpne L3;
				L2:	sconst_1;
					sreturn;
				L3:	bspush 111;
					bspush 23;
					invokestatic 64;		// javacard/framework/Util.makeShort(BB)S
					invokestatic 68;		// javacard/framework/ISOException.throwIt(S)V
					goto L5;
				L4:	bspush 111;
					bspush 22;
					invokestatic 64;		// javacard/framework/Util.makeShort(BB)S
					invokestatic 68;		// javacard/framework/ISOException.throwIt(S)V
				L5:	sconst_0;
					sreturn;
		}

		.method public destroyEnv()Z 3 {
			.stack 1;
			.locals 0;

				L0:	getstatic_a 54;		// reference thetapass/ThetaPassApplet.api
					invokeinterface 1 56 2;		// KM101/T101OpenAPI
					sreturn;
		}

		.method public authContainer([BSS[BS[B)S 4 {
			.stack 16;
			.locals 0;

				L0:	aload 6;
					sconst_0;
					sconst_4;
					bastore;
					aload_1;
					sload_2;
					aload 6;
					sconst_1;
					sload_3;
					invokestatic 51;		// javacard/framework/Util.arrayCopyNonAtomic([BS[BSS)S
					pop;
					aload 4;
					sload 5;
					aload 6;
					sconst_1;
					sload_3;
					sadd;
					bspush 8;
					invokestatic 51;		// javacard/framework/Util.arrayCopyNonAtomic([BS[BSS)S
					pop;
					getstatic_a 54;		// reference thetapass/ThetaPassApplet.api
					aload 6;
					sconst_0;
					baload;
					aload 6;
					sconst_1;
					sload_3;
					aload 6;
					sconst_1;
					sload_3;
					sadd;
					bspush 8;
					aload 6;
					bspush 9;
					sload_3;
					sadd;
					aload 6;
					bspush 73;
					sload_3;
					sadd;
					aload 6;
					sspush 137;
					sload_3;
					sadd;
					aload 6;
					sspush 201;
					invokeinterface 16 56 23;		// KM101/T101OpenAPI
					pop;
					getstatic_a 54;		// reference thetapass/ThetaPassApplet.api
					aload 6;
					sspush 201;
					bspush 32;
					aload 6;
					sconst_0;
					invokeinterface 6 56 20;		// KM101/T101OpenAPI
					sreturn;
		}

		.method public finalizeContainer([BSS[B)Z 5 {
			.stack 7;
			.locals 0;

				L0:	getstatic_a 54;		// reference thetapass/ThetaPassApplet.api
					aload 4;
					sconst_0;
					invokeinterface 3 56 1;		// KM101/T101OpenAPI
					ifeq L3;
				L1:	aload 4;
					sconst_0;
					getfield_a_this 0;		// reference thetapass/APIShim.nonceBuffer
					sconst_0;
					bspush 8;
					invokestatic 51;		// javacard/framework/Util.arrayCopyNonAtomic([BS[BSS)S
					pop;
					aload_0;
					aload_1;
					sload_2;
					sload_3;
					getfield_a_this 0;		// reference thetapass/APIShim.nonceBuffer
					sconst_0;
					aload 4;
					invokevirtual 70;		// authContainer([BSS[BS[B)S
					sconst_1;
					if_scmpne L3;
				L2:	sconst_1;
					sreturn;
				L3:	sconst_0;
					sreturn;
		}

		.method public confirmationUI([BSS[BSS[B)Z 6 {
			.stack 16;
			.locals 0;

				L0:	aload_0;
					sconst_2;
					sconst_0;
					sconst_0;
					sconst_0;
					sconst_0;
					aload_1;
					sload_2;
					sload_3;
					aload 4;
					sload 5;
					sload 6;
					getfield_a_this 3;		// reference thetapass/APIShim.aocPin
					sconst_0;
					getfield_a_this 3;		// reference thetapass/APIShim.aocPin
					arraylength;
					aload 7;
					invokevirtual 72;		// uxRender(BBBBB[BSS[BSS[BSS[B)S
					sconst_1;
					if_scmpne L2;
				L1:	sconst_1;
					sreturn;
				L2:	sconst_0;
					sreturn;
		}

		.method public opsStatusUI(Z[BSS[B)V 7 {
			.stack 16;
			.locals 0;

				L0:	sload_1;
					ifeq L2;
				L1:	aload_0;
					sconst_2;
					sconst_0;
					sconst_0;
					sconst_0;
					sconst_0;
					aload_2;
					sload_3;
					sload 4;
					getstatic_a 76;		// reference thetapass/APIShim.TXT_SUCCESS
					sconst_0;
					getstatic_a 76;		// reference thetapass/APIShim.TXT_SUCCESS
					arraylength;
					getfield_a_this 3;		// reference thetapass/APIShim.aocPin
					sconst_0;
					getfield_a_this 3;		// reference thetapass/APIShim.aocPin
					arraylength;
					aload 5;
					invokevirtual 72;		// uxRender(BBBBB[BSS[BSS[BSS[B)S
					pop;
					goto L3;
				L2:	aload_0;
					sconst_2;
					sconst_0;
					sconst_0;
					sconst_0;
					sconst_0;
					aload_2;
					sload_3;
					sload 4;
					getstatic_a 22;		// reference thetapass/APIShim.TXT_FAILED
					sconst_0;
					getstatic_a 22;		// reference thetapass/APIShim.TXT_FAILED
					arraylength;
					getfield_a_this 3;		// reference thetapass/APIShim.aocPin
					sconst_0;
					getfield_a_this 3;		// reference thetapass/APIShim.aocPin
					arraylength;
					aload 5;
					invokevirtual 72;		// uxRender(BBBBB[BSS[BSS[BSS[B)S
					pop;
				L3:	return;
		}

		.method public opsCancelStatusUI([BSS[B)V 8 {
			.stack 16;
			.locals 0;

				L0:	aload_0;
					sconst_2;
					sconst_0;
					sconst_0;
					sconst_0;
					sconst_0;
					aload_1;
					sload_2;
					sload_3;
					getstatic_a 23;		// reference thetapass/APIShim.TXT_CANCELLED
					sconst_0;
					getstatic_a 23;		// reference thetapass/APIShim.TXT_CANCELLED
					arraylength;
					getfield_a_this 3;		// reference thetapass/APIShim.aocPin
					sconst_0;
					getfield_a_this 3;		// reference thetapass/APIShim.aocPin
					arraylength;
					aload 4;
					invokevirtual 72;		// uxRender(BBBBB[BSS[BSS[BSS[B)S
					pop;
					return;
		}

		.method public pinInputUI([BSS[BSS[B)S 9 {
			.stack 16;
			.locals 0;

				L0:	aload_0;
					sconst_4;
					sconst_1;
					sconst_1;
					sconst_m1;
					bspush 32;
					aload_1;
					sload_2;
					sload_3;
					aload 4;
					sload 5;
					sload 6;
					getfield_a_this 3;		// reference thetapass/APIShim.aocPin
					sconst_0;
					getfield_a_this 3;		// reference thetapass/APIShim.aocPin
					arraylength;
					aload 7;
					invokevirtual 72;		// uxRender(BBBBB[BSS[BSS[BSS[B)S
					sreturn;
		}

		.method public mainMenuUI([B)S 10 {
			.stack 16;
			.locals 0;

				L0:	aload_0;
					sconst_5;
					sconst_m1;
					sconst_5;
					sconst_0;
					sconst_0;
					getstatic_a 52;		// reference thetapass/APIShim.appName
					sconst_0;
					getstatic_a 52;		// reference thetapass/APIShim.appName
					arraylength;
					getstatic_a 24;		// reference thetapass/APIShim.TXT_CRED_MENU_LIST
					sconst_0;
					getstatic_a 24;		// reference thetapass/APIShim.TXT_CRED_MENU_LIST
					arraylength;
					getfield_a_this 3;		// reference thetapass/APIShim.aocPin
					sconst_0;
					getfield_a_this 3;		// reference thetapass/APIShim.aocPin
					arraylength;
					aload_1;
					invokevirtual 72;		// uxRender(BBBBB[BSS[BSS[BSS[B)S
					sreturn;
		}

		.method public showMenuKeyQR([B[B)S 11 {
			.stack 16;
			.locals 0;

				L0:	aload_0;
					sconst_3;
					sconst_1;
					sconst_1;
					sconst_m1;
					bspush 32;
					getstatic_a 52;		// reference thetapass/APIShim.appName
					sconst_0;
					getstatic_a 52;		// reference thetapass/APIShim.appName
					arraylength;
					aload_1;
					sconst_1;
					aload_1;
					sconst_0;
					baload;
					sspush 255;
					sand;
					getfield_a_this 3;		// reference thetapass/APIShim.aocPin
					sconst_0;
					getfield_a_this 3;		// reference thetapass/APIShim.aocPin
					arraylength;
					aload_2;
					invokevirtual 72;		// uxRender(BBBBB[BSS[BSS[BSS[B)S
					sreturn;
		}

		.method public showScrollingList([BSSS[BSS[B)S 12 {
			.stack 16;
			.locals 0;

				L0:	aload_0;
					sconst_5;
					sconst_0;
					sload 4;
					sspush 255;
					sand;
					s2b;
					sconst_0;
					sconst_0;
					aload_1;
					sload_2;
					sload_3;
					aload 5;
					sload 6;
					sload 7;
					getfield_a_this 3;		// reference thetapass/APIShim.aocPin
					sconst_0;
					getfield_a_this 3;		// reference thetapass/APIShim.aocPin
					arraylength;
					aload 8;
					invokevirtual 72;		// uxRender(BBBBB[BSS[BSS[BSS[B)S
					sreturn;
		}

		.method public uxRender(BBBBB[BSS[BSS[BSS[B)S 13 {
			.stack 15;
			.locals 3;

				L0:	aload 15;
					sconst_0;
					sload_1;
					bastore;
					sconst_0;
					sstore 16;
				L1:	sconst_0;
					sstore 17;
				L2:	sconst_0;
					sstore 18;
				L3:	aload 6;
					ifnull L6;
				L4:	sload 8;
					ifle L6;
				L5:	aload 6;
					sload 7;
					aload 15;
					sconst_1;
					sload 8;
					invokestatic 51;		// javacard/framework/Util.arrayCopyNonAtomic([BS[BSS)S
					pop;
					sload 8;
					sstore 17;
				L6:	aload 9;
					ifnull L9;
				L7:	sload 11;
					ifle L9;
				L8:	aload 9;
					sload 10;
					aload 15;
					sconst_1;
					sload 17;
					sadd;
					sload 11;
					invokestatic 51;		// javacard/framework/Util.arrayCopyNonAtomic([BS[BSS)S
					pop;
					sload 11;
					sstore 18;
				L9:	getstatic_a 54;		// reference thetapass/ThetaPassApplet.api
					aload 15;
					sconst_0;
					baload;
					sload_2;
					sload_3;
					sload 4;
					sload 5;
					aload 15;
					sconst_1;
					sload 17;
					aload 15;
					sconst_1;
					sload 17;
					sadd;
					sload 18;
					aload 15;
					sconst_1;
					sload 17;
					sadd;
					sload 18;
					sadd;
					invokeinterface 14 56 24;		// KM101/T101OpenAPI
					sstore 16;
					sload 16;
					sconst_m1;
					if_scmpeq L13;
				L10:	aload 15;
					sconst_1;
					sload 17;
					sadd;
					sload 18;
					sadd;
					getfield_a_this 0;		// reference thetapass/APIShim.nonceBuffer
					sconst_0;
					bspush 8;
					invokestatic 51;		// javacard/framework/Util.arrayCopyNonAtomic([BS[BSS)S
					pop;
					aload_0;
					aload 12;
					sload 13;
					sload 14;
					getfield_a_this 0;		// reference thetapass/APIShim.nonceBuffer
					sconst_0;
					aload 15;
					invokevirtual 70;		// authContainer([BSS[BS[B)S
					sstore 16;
					sload 16;
					sconst_m1;
					if_scmple L12;
				L11:	sload 16;
					sreturn;
				L12:	bspush 111;
					bspush -62;
					invokestatic 64;		// javacard/framework/Util.makeShort(BB)S
					invokestatic 68;		// javacard/framework/ISOException.throwIt(S)V
					goto L14;
				L13:	bspush 111;
					bspush -63;
					invokestatic 64;		// javacard/framework/Util.makeShort(BB)S
					invokestatic 68;		// javacard/framework/ISOException.throwIt(S)V
				L14:	sconst_m1;
					sreturn;
		}

		.method public static shortToBytes(S[BS)V 1 {
			.stack 4;
			.locals 0;

				L0:	aload_1;
					sload_2;
					sload_0;
					bspush 8;
					sshr;
					sspush 255;
					sand;
					s2b;
					bastore;
					aload_1;
					sload_2;
					sconst_1;
					sadd;
					sload_0;
					sspush 255;
					sand;
					s2b;
					bastore;
					return;
		}

		.method public static toDecimalASCII([BSS[BS)S 2 {
			.stack 4;
			.locals 6;

				L0:	getstatic_a 25;		// reference thetapass/APIShim.BCD_SIZE_PER_BYTES
					sload_2;
					baload;
					sstore 5;
				L1:	sconst_0;
					sstore 9;
				L2:	goto L11;
				L3:	sconst_0;
					sstore 8;
				L4:	sconst_0;
					sstore 10;
				L5:	goto L9;
				L6:	aload_0;
					sload_1;
					sload 10;
					sadd;
					baload;
					sspush 255;
					sand;
					sstore 6;
				L7:	sload 8;
					sspush 256;
					smul;
					sload 6;
					sadd;
					sstore 7;
				L8:	sload 7;
					bspush 10;
					srem;
					sstore 8;
					aload_0;
					sload_1;
					sload 10;
					sadd;
					sload 7;
					bspush 10;
					sdiv;
					s2b;
					bastore;
					sinc 10 1;
				L9:	sload 10;
					sload_2;
					if_scmplt L6;
				L10:	aload_3;
					sload 4;
					sload 5;
					sadd;
					sload 9;
					ssub;
					sconst_1;
					ssub;
					sload 8;
					bspush 48;
					sadd;
					s2b;
					bastore;
					sinc 9 1;
				L11:	sload 9;
					sload 5;
					if_scmplt L3;
				L12:	sload 5;
					sreturn;
		}

	}

	.class public Codec 1 extends 0.0 {		// extends java/lang/Object

		.fields {
			public static final byte[] BCD_SIZE_PER_BYTES 0 = {0,3,5,8,10,13,15,17,20,22,25,27,29,32,34,37,39,41,44,46,49,51,53,56,58,61,63,66,68,70,73,75,78};		// [B
		}

		.publicMethodTable 1 {
			equals(Ljava/lang/Object;)Z;
		}

		.packageMethodTable 0 {
		}

		.method public <init>()V 0 {
			.stack 1;
			.locals 0;

				L0:	aload_0;
					invokespecial 37;		// java/lang/Object.<init>()V
					return;
		}

		.method public static toDecimalASCII([BSS[BS)S 1 {
			.stack 4;
			.locals 6;

				L0:	getstatic_a 26;		// reference thetapass/Codec.BCD_SIZE_PER_BYTES
					sload_2;
					baload;
					sstore 5;
				L1:	sconst_0;
					sstore 9;
				L2:	goto L11;
				L3:	sconst_0;
					sstore 8;
				L4:	sconst_0;
					sstore 10;
				L5:	goto L9;
				L6:	aload_0;
					sload_1;
					sload 10;
					sadd;
					baload;
					sspush 255;
					sand;
					sstore 6;
				L7:	sload 8;
					sspush 256;
					smul;
					sload 6;
					sadd;
					sstore 7;
				L8:	sload 7;
					bspush 10;
					srem;
					sstore 8;
					aload_0;
					sload_1;
					sload 10;
					sadd;
					sload 7;
					bspush 10;
					sdiv;
					s2b;
					bastore;
					sinc 10 1;
				L9:	sload 10;
					sload_2;
					if_scmplt L6;
				L10:	aload_3;
					sload 4;
					sload 5;
					sadd;
					sload 9;
					ssub;
					sconst_1;
					ssub;
					sload 8;
					bspush 48;
					sadd;
					s2b;
					bastore;
					sinc 9 1;
				L11:	sload 9;
					sload 5;
					if_scmplt L3;
				L12:	sload 5;
					sreturn;
		}

		.method public static intToBytes(I[BS)V 2 {
			.stack 6;
			.locals 0;

				L0:	aload_2;
					sload_3;
					iload_0;
					bipush 24;
					ishr;
					sipush 255;
					iand;
					i2b;
					bastore;
					aload_2;
					sload_3;
					sconst_1;
					sadd;
					iload_0;
					bipush 16;
					ishr;
					sipush 255;
					iand;
					i2b;
					bastore;
					aload_2;
					sload_3;
					sconst_2;
					sadd;
					iload_0;
					bipush 8;
					ishr;
					sipush 255;
					iand;
					i2b;
					bastore;
					aload_2;
					sload_3;
					sconst_3;
					sadd;
					iload_0;
					sipush 255;
					iand;
					i2b;
					bastore;
					return;
		}

		.method public static bytesToInt(BBBB)I 3 {
			.stack 6;
			.locals 0;

				L0:	sload_0;
					s2i;
					sipush 255;
					iand;
					bipush 24;
					ishl;
					sload_1;
					s2i;
					sipush 255;
					iand;
					bipush 16;
					ishl;
					ior;
					sload_2;
					s2i;
					sipush 255;
					iand;
					bipush 8;
					ishl;
					ior;
					sload_3;
					s2i;
					sipush 255;
					iand;
					iconst_0;
					ishl;
					ior;
					ireturn;
		}

		.method public static shortToBytes(S[BS)V 4 {
			.stack 4;
			.locals 0;

				L0:	aload_1;
					sload_2;
					sload_0;
					bspush 8;
					sshr;
					sspush 255;
					sand;
					s2b;
					bastore;
					aload_1;
					sload_2;
					sconst_1;
					sadd;
					sload_0;
					sspush 255;
					sand;
					s2b;
					bastore;
					return;
		}

		.method public static bytesToShort(BB)S 5 {
			.stack 3;
			.locals 0;

				L0:	sload_0;
					sspush 255;
					sand;
					bspush 8;
					sshl;
					sload_1;
					sspush 255;
					sand;
					sconst_0;
					sshl;
					sor;
					sreturn;
		}

		.method public static isInputAllowable([BSSZ)Z 6 {
			.stack 2;
			.locals 2;

				L0:	sload_1;
					sstore 4;
				L1:	goto L15;
				L2:	aload_0;
					sload 4;
					baload;
					sstore 5;
				L3:	sload_3;
					ifeq L7;
				L4:	sload 5;
					bspush 32;
					if_scmplt L6;
				L5:	sload 5;
					bspush 126;
					if_scmple L14;
				L6:	bspush 111;
					sload 5;
					invokestatic 64;		// javacard/framework/Util.makeShort(BB)S
					invokestatic 68;		// javacard/framework/ISOException.throwIt(S)V
					sconst_0;
					sreturn;
				L7:	sload 5;
					bspush 48;
					if_scmplt L9;
				L8:	sload 5;
					bspush 57;
					if_scmple L14;
				L9:	sload 5;
					bspush 65;
					if_scmplt L11;
				L10:	sload 5;
					bspush 90;
					if_scmple L14;
				L11:	sload 5;
					bspush 97;
					if_scmplt L13;
				L12:	sload 5;
					bspush 122;
					if_scmple L14;
				L13:	bspush 106;
					sload 5;
					invokestatic 64;		// javacard/framework/Util.makeShort(BB)S
					invokestatic 68;		// javacard/framework/ISOException.throwIt(S)V
					sconst_0;
					sreturn;
				L14:	sinc 4 1;
				L15:	sload 4;
					sload_2;
					if_scmplt L2;
				L16:	sconst_1;
					sreturn;
		}

	}

	.class public ECC 2 extends 0.0 {		// extends java/lang/Object

		.fields {
			public static final byte ALG_EC_SVDP_DH_PLAIN_XY = 6;		// B
			protected static byte[] EC_P256R1_FIELD_A 0 = {-1,-1,-1,-1,0,0,0,1,0,0,0,0,0,0,0,0,0,0,0,0,-1,-1,-1,-1,-1,-1,-1,-1,-1,-1,-1,-4};		// [B
			protected static byte[] EC_P256R1_FIELD_B 1 = {90,-58,53,-40,-86,58,-109,-25,-77,-21,-67,85,118,-104,-122,-68,101,29,6,-80,-52,83,-80,-10,59,-50,60,62,39,-46,96,75};		// [B
			protected static byte[] EC_P256R1_FIELD_G 2 = {4,107,23,-47,-14,-31,44,66,71,-8,-68,-26,-27,99,-92,64,-14,119,3,125,-127,45,-21,51,-96,-12,-95,57,69,-40,-104,-62,-106,79,-29,66,-30,-2,26,127,-101,-114,-25,-21,74,124,15,-98,22,43,-50,51,87,107,49,94,-50,-53,-74,64,104,55,-65,81,-11};		// [B
			protected static byte[] EC_P256R1_FIELD_R 3 = {-1,-1,-1,-1,0,0,0,0,-1,-1,-1,-1,-1,-1,-1,-1,-68,-26,-6,-83,-89,23,-98,-124,-13,-71,-54,-62,-4,99,37,81};		// [B
			protected static byte[] EC_P256R1_FP 4 = {-1,-1,-1,-1,0,0,0,1,0,0,0,0,0,0,0,0,0,0,0,0,-1,-1,-1,-1,-1,-1,-1,-1,-1,-1,-1,-1};		// [B
			static final byte K = 1;		// B
			static final short KEY_SIZE = 256;		// S
		}

		.publicMethodTable 1 {
			equals(Ljava/lang/Object;)Z;
		}

		.packageMethodTable 0 {
		}

		.method public <init>()V 0 {
			.stack 1;
			.locals 0;

				L0:	aload_0;
					invokespecial 37;		// java/lang/Object.<init>()V
					return;
		}

		.method public static setCurveParameters(Ljavacard/security/ECKey;)V 1 {
			.stack 4;
			.locals 0;

			.descriptor	Ljavacard/security/ECKey;	2.17;

				L0:	aload_0;
					getstatic_a 27;		// reference thetapass/ECC.EC_P256R1_FIELD_A
					sconst_0;
					getstatic_a 27;		// reference thetapass/ECC.EC_P256R1_FIELD_A
					arraylength;
					invokeinterface 4 28 3;		// javacard/security/ECKey
					aload_0;
					getstatic_a 29;		// reference thetapass/ECC.EC_P256R1_FIELD_B
					sconst_0;
					getstatic_a 29;		// reference thetapass/ECC.EC_P256R1_FIELD_B
					arraylength;
					invokeinterface 4 28 4;		// javacard/security/ECKey
					aload_0;
					getstatic_a 30;		// reference thetapass/ECC.EC_P256R1_FP
					sconst_0;
					getstatic_a 30;		// reference thetapass/ECC.EC_P256R1_FP
					arraylength;
					invokeinterface 4 28 0;		// javacard/security/ECKey
					aload_0;
					getstatic_a 31;		// reference thetapass/ECC.EC_P256R1_FIELD_G
					sconst_0;
					getstatic_a 31;		// reference thetapass/ECC.EC_P256R1_FIELD_G
					arraylength;
					invokeinterface 4 28 5;		// javacard/security/ECKey
					aload_0;
					getstatic_a 32;		// reference thetapass/ECC.EC_P256R1_FIELD_R
					sconst_0;
					getstatic_a 32;		// reference thetapass/ECC.EC_P256R1_FIELD_R
					arraylength;
					invokeinterface 4 28 6;		// javacard/security/ECKey
					aload_0;
					sconst_1;
					invokeinterface 2 28 7;		// javacard/security/ECKey
					return;
		}

		.method public static checkCurveParameters(Ljavacard/security/ECKey;[BS)Z 2 {
			.stack 5;
			.locals 0;

			.descriptor	Ljavacard/security/ECKey;	2.17;

				L0:	aload_0;
					aload_1;
					sload_2;
					invokeinterface 3 28 9;		// javacard/security/ECKey
					pop;
					aload_1;
					sload_2;
					getstatic_a 27;		// reference thetapass/ECC.EC_P256R1_FIELD_A
					sconst_0;
					getstatic_a 27;		// reference thetapass/ECC.EC_P256R1_FIELD_A
					arraylength;
					invokestatic 33;		// javacard/framework/Util.arrayCompare([BS[BSS)B
					ifeq L2;
				L1:	sconst_0;
					sreturn;
				L2:	aload_0;
					aload_1;
					sload_2;
					invokeinterface 3 28 10;		// javacard/security/ECKey
					pop;
					aload_1;
					sload_2;
					getstatic_a 29;		// reference thetapass/ECC.EC_P256R1_FIELD_B
					sconst_0;
					getstatic_a 29;		// reference thetapass/ECC.EC_P256R1_FIELD_B
					arraylength;
					invokestatic 33;		// javacard/framework/Util.arrayCompare([BS[BSS)B
					ifeq L4;
				L3:	sconst_0;
					sreturn;
				L4:	aload_0;
					aload_1;
					sload_2;
					invokeinterface 3 28 11;		// javacard/security/ECKey
					pop;
					aload_1;
					sload_2;
					getstatic_a 31;		// reference thetapass/ECC.EC_P256R1_FIELD_G
					sconst_0;
					getstatic_a 31;		// reference thetapass/ECC.EC_P256R1_FIELD_G
					arraylength;
					invokestatic 33;		// javacard/framework/Util.arrayCompare([BS[BSS)B
					ifeq L6;
				L5:	sconst_0;
					sreturn;
				L6:	aload_0;
					aload_1;
					sload_2;
					invokeinterface 3 28 12;		// javacard/security/ECKey
					pop;
					aload_1;
					sload_2;
					getstatic_a 32;		// reference thetapass/ECC.EC_P256R1_FIELD_R
					sconst_0;
					getstatic_a 32;		// reference thetapass/ECC.EC_P256R1_FIELD_R
					arraylength;
					invokestatic 33;		// javacard/framework/Util.arrayCompare([BS[BSS)B
					ifeq L8;
				L7:	sconst_0;
					sreturn;
				L8:	aload_0;
					aload_1;
					sload_2;
					invokeinterface 3 28 8;		// javacard/security/ECKey
					pop;
					aload_1;
					sload_2;
					getstatic_a 30;		// reference thetapass/ECC.EC_P256R1_FP
					sconst_0;
					getstatic_a 30;		// reference thetapass/ECC.EC_P256R1_FP
					arraylength;
					invokestatic 33;		// javacard/framework/Util.arrayCompare([BS[BSS)B
					ifeq L10;
				L9:	sconst_0;
					sreturn;
				L10:	aload_0;
					invokeinterface 1 28 13;		// javacard/security/ECKey
					sconst_1;
					if_scmpeq L12;
				L11:	sconst_0;
					sreturn;
				L12:	sconst_1;
					sreturn;
		}

	}

	.class public ThetaPassApplet 3 extends 1.3 {		// extends javacard/framework/Applet

		.fields {
			public 1.6 apiAID 0;		// Ljavacard/framework/AID;
			private 4.1 cipher 1;		// Ljavacardx/crypto/Cipher;
			private 4.1 cipherNoPad 2;		// Ljavacardx/crypto/Cipher;
			private 2.22 ecdh 3;		// Ljavacard/security/KeyAgreement;
			private 2.11 md 4;		// Ljavacard/security/MessageDigest;
			private byte[] defaultPin 5;		// [B
			private byte[] fs 6;		// [B
			private byte[] fsIV 7;		// [B
			private 2.20 fsKey 8;		// Ljavacard/security/AESKey;
			private 2.20 sessKey 9;		// Ljavacard/security/AESKey;
			private 1.9 pin 10;		// Ljavacard/framework/OwnerPIN;
			private 2.16 kp 11;		// Ljavacard/security/KeyPair;
			private 2.18 privKey 12;		// Ljavacard/security/ECPrivateKey;
			private 2.19 pubKey 13;		// Ljavacard/security/ECPublicKey;
			private byte[] b0 14;		// [B
			private byte[] b1 15;		// [B
			private byte[] b2 16;		// [B
			private short[] sb 17;		// [S
			public static final short APP_VERSION = 0;		// S
			public static final short PROTO_VERSION = 0;		// S
			public static final byte CLA = -80;		// B
			public static final byte INS_MAIN_MENU = 16;		// B
			public static final byte INS_OPEN_SCHANNEL = 80;		// B
			public static final byte INS_AUTHENTICATE = -126;		// B
			public static final byte INS_UPDATE_AUTH = -125;		// B
			public static final byte INS_GET_RECORD = -54;		// B
			public static final byte INS_PUT_RECORD = -38;		// B
			public static final byte INS_DELETE_RECORD = -22;		// B
			public static final short FS_TOTAL_RECORDS = 64;		// S
			public static final short FS_OFF_FLAG_SETTING = 0;		// S
			public static final short FS_OFF_FLAG_ENAME0_LEN = 1;		// S
			public static final short FS_OFF_FLAG_ENAME1_LEN = 2;		// S
			public static final short FS_OFF_FLAG_CONTENT_LEN = 3;		// S
			public static final short FS_OFF_ENAME0 = 4;		// S
			public static final short FS_OFF_ENAME1 = 19;		// S
			public static final short FS_OFF_CONTENT = 67;		// S
			public static final short FS_MAX_ENAME0_LEN = 15;		// S
			public static final short FS_MAX_ENAME1_LEN = 48;		// S
			public static final short FS_MAX_CONTENT = 80;		// S
			public static final short FS_MAX_RECORD = 147;		// S
			public static final byte FS_FLAG_ISACTIVE = -128;		// B
			public static final byte FS_FLAG_REQUIRE_AUTH = 64;		// B
			public static final byte FS_FLAG_HIDE_UNLESS_AUTH = 32;		// B
			public static final byte FS_FLAG_TYPE_OTP = 1;		// B
			public static final byte FS_FLAG_TYPE_PWD = 2;		// B
			public static final byte FS_FLAG_TYPE_QR = 3;		// B
			public static final byte FS_FLAG_TYPE_TXT = 4;		// B
			public static final byte FS_FLAG_TYPE_ORGANIZER = 5;		// B
			public static final byte FS_FLAG_TYPE_FIDO = 6;		// B
			public static final short PIN_DEFAULT_RETRY = 5;		// S
			public static final short PIN_DEFAULT_MAX_LEN = 32;		// S
			public static final short PIN_DEFAULT_MIN_LEN = 4;		// S
			public static final short SW_CARD_NOT_READY = 28447;		// S
			public static final short SW_SCHANNEL_REQ_INIT = 28620;		// S
			public static final short SW_SCHANNEL_ERROR = 28621;		// S
			public static final short SW_FS_ERROR = 28465;		// S
			public static final short SW_UI_ERROR = 28497;		// S
			public static 2.14 randomData 0;		// Ljavacard/security/RandomData;
			public static 3.1 api 1;		// LKM101/T101OpenAPI;
			public static APIShim apishim 2;		// Lthetapass/APIShim;
			public static byte[] serverAID 3 = {75,77,49,48,49,0};		// [B
		}

		.publicMethodTable 7 {
			equals(Ljava/lang/Object;)Z;
			register()V;
			register([BSB)V;
			selectingApplet()Z;
			deselect()V;
			getShareableInterfaceObject(Ljavacard/framework/AID;B)Ljavacard/framework/Shareable;;
			select()Z;
			process(Ljavacard/framework/APDU;)V;
			uninstall()V;
		}

		.packageMethodTable 0 {
		}

		.implementedInterfaceInfoTable { 
			.interface 1.18 { 		// javacard/framework/AppletEvent
				8;		// uninstall()V
			}

		}

		.method private final initAPI([B)V {
			.stack 4;
			.locals 1;

				L0:	getstatic_a 54;		// reference thetapass/ThetaPassApplet.api
					ifnonnull L15;
				L1:	aload_0;
					getstatic_a 35;		// reference thetapass/ThetaPassApplet.serverAID
					sconst_0;
					getstatic_a 35;		// reference thetapass/ThetaPassApplet.serverAID
					arraylength;
					s2b;
					invokestatic 36;		// javacard/framework/JCSystem.lookupAID([BSB)Ljavacard/framework/AID;
					putfield_a 4;		// reference thetapass/ThetaPassApplet.apiAID
				L2:	goto L5;
				L3:	astore_2;
				L4:	sspush 27267;
					invokestatic 68;		// javacard/framework/ISOException.throwIt(S)V
				L5:	getfield_a_this 4;		// reference thetapass/ThetaPassApplet.apiAID
					ifnull L14;
				L6:	getfield_a_this 4;		// reference thetapass/ThetaPassApplet.apiAID
					sconst_0;
					invokestatic 38;		// javacard/framework/JCSystem.getAppletShareableInterfaceObject(Ljavacard/framework/AID;B)Ljavacard/framework/Shareable;
					checkcast 0 56;		// T_CLASSORINTERFACE KM101/T101OpenAPI
					putstatic_a 54;		// reference thetapass/ThetaPassApplet.api
				L7:	goto L10;
				L8:	astore_2;
				L9:	sspush 27033;
					invokestatic 68;		// javacard/framework/ISOException.throwIt(S)V
				L10:	getstatic_a 54;		// reference thetapass/ThetaPassApplet.api
					ifnonnull L12;
				L11:	sspush 27033;
					invokestatic 68;		// javacard/framework/ISOException.throwIt(S)V
				L12:	new 39;		// thetapass/APIShim
					dup;
					invokespecial 40;		// thetapass/APIShim.<init>()V
					putstatic_a 41;		// reference thetapass/ThetaPassApplet.apishim
					getstatic_a 54;		// reference thetapass/ThetaPassApplet.api
					invokeinterface 1 56 2;		// KM101/T101OpenAPI
					pop;
					getstatic_a 41;		// reference thetapass/ThetaPassApplet.apishim
					aload_1;
					invokevirtual 42;		// initEnv([B)Z
					ifne L15;
				L13:	sspush 27267;
					invokestatic 68;		// javacard/framework/ISOException.throwIt(S)V
					goto L15;
				L14:	sspush 27013;
					invokestatic 68;		// javacard/framework/ISOException.throwIt(S)V
				L15:	return;
			.exceptionTable {
				// start_block end_block handler_block catch_type_index
				L1 L2 L3 34;
				L6 L7 L8 34;
			}
		}

		.method public static install([BSB)V 0 {
			.stack 1;
			.locals 0;

				L0:	new 43;		// thetapass/ThetaPassApplet
					invokespecial 44;		// thetapass/ThetaPassApplet.<init>()V
					return;
		}

		.method protected <init>()V 1 {
			.stack 5;
			.locals 0;

				L0:	aload_0;
					invokespecial 45;		// javacard/framework/Applet.<init>()V
					aload_0;
					aconst_null;
					putfield_a 5;		// reference thetapass/ThetaPassApplet.cipher
					aload_0;
					aconst_null;
					putfield_a 6;		// reference thetapass/ThetaPassApplet.cipherNoPad
					aload_0;
					aconst_null;
					putfield_a 7;		// reference thetapass/ThetaPassApplet.ecdh
					aload_0;
					aconst_null;
					putfield_a 8;		// reference thetapass/ThetaPassApplet.md
					aload_0;
					aconst_null;
					putfield_a 4;		// reference thetapass/ThetaPassApplet.apiAID
					aload_0;
					sconst_4;
					newarray 11;
					dup;
					sconst_0;
					bspush 49;
					bastore;
					dup;
					sconst_1;
					bspush 50;
					bastore;
					dup;
					sconst_2;
					bspush 51;
					bastore;
					dup;
					sconst_3;
					bspush 52;
					bastore;
					putfield_a 9;		// reference thetapass/ThetaPassApplet.defaultPin
					aload_0;
					aconst_null;
					putfield_a 10;		// reference thetapass/ThetaPassApplet.sessKey
					aload_0;
					sspush 240;
					sconst_1;
					invokestatic 46;		// javacard/framework/JCSystem.makeTransientByteArray(SB)[B
					putfield_a 11;		// reference thetapass/ThetaPassApplet.b0
					aload_0;
					sconst_4;
					sconst_1;
					invokestatic 46;		// javacard/framework/JCSystem.makeTransientByteArray(SB)[B
					putfield_a 12;		// reference thetapass/ThetaPassApplet.b1
					aload_0;
					bspush 16;
					sconst_1;
					invokestatic 46;		// javacard/framework/JCSystem.makeTransientByteArray(SB)[B
					putfield_a 13;		// reference thetapass/ThetaPassApplet.b2
					aload_0;
					sconst_3;
					sconst_1;
					invokestatic 55;		// javacard/framework/JCSystem.makeTransientShortArray(SB)[S
					putfield_a 14;		// reference thetapass/ThetaPassApplet.sb
					aload_0;
					sspush 9408;
					newarray 11;
					putfield_a 15;		// reference thetapass/ThetaPassApplet.fs
					aload_0;
					bspush 16;
					newarray 11;
					putfield_a 16;		// reference thetapass/ThetaPassApplet.fsIV
					sconst_2;
					invokestatic 59;		// javacard/security/RandomData.getInstance(B)Ljavacard/security/RandomData;
					putstatic_a 48;		// reference thetapass/ThetaPassApplet.randomData
					aload_0;
					bspush 24;
					sconst_0;
					invokestatic 60;		// javacardx/crypto/Cipher.getInstance(BZ)Ljavacardx/crypto/Cipher;
					putfield_a 5;		// reference thetapass/ThetaPassApplet.cipher
					aload_0;
					bspush 13;
					sconst_0;
					invokestatic 60;		// javacardx/crypto/Cipher.getInstance(BZ)Ljavacardx/crypto/Cipher;
					putfield_a 6;		// reference thetapass/ThetaPassApplet.cipherNoPad
					aload_0;
					sconst_4;
					sconst_0;
					invokestatic 61;		// javacard/security/MessageDigest.getInstance(BZ)Ljavacard/security/MessageDigest;
					putfield_a 8;		// reference thetapass/ThetaPassApplet.md
					aload_0;
					new 62;		// javacard/framework/OwnerPIN
					dup;
					sconst_5;
					bspush 32;
					invokespecial 63;		// javacard/framework/OwnerPIN.<init>(BB)V
					putfield_a 17;		// reference thetapass/ThetaPassApplet.pin
					getfield_a_this 17;		// reference thetapass/ThetaPassApplet.pin
					getfield_a_this 9;		// reference thetapass/ThetaPassApplet.defaultPin
					sconst_0;
					getfield_a_this 9;		// reference thetapass/ThetaPassApplet.defaultPin
					arraylength;
					sspush 255;
					sand;
					s2b;
					invokevirtual 65;		// update([BSB)V
					aload_0;
					bspush 15;
					sspush 256;
					sconst_0;
					invokestatic 66;		// javacard/security/KeyBuilder.buildKey(BSZ)Ljavacard/security/Key;
					checkcast 0 67;		// T_CLASSORINTERFACE javacard/security/AESKey
					putfield_a 18;		// reference thetapass/ThetaPassApplet.fsKey
					aload_0;
					bspush 13;
					sspush 256;
					sconst_0;
					invokestatic 66;		// javacard/security/KeyBuilder.buildKey(BSZ)Ljavacard/security/Key;
					checkcast 0 67;		// T_CLASSORINTERFACE javacard/security/AESKey
					putfield_a 10;		// reference thetapass/ThetaPassApplet.sessKey
					getstatic_a 48;		// reference thetapass/ThetaPassApplet.randomData
					getfield_a_this 11;		// reference thetapass/ThetaPassApplet.b0
					sconst_0;
					bspush 32;
					invokevirtual 49;		// generateData([BSS)V
					getfield_a_this 18;		// reference thetapass/ThetaPassApplet.fsKey
					getfield_a_this 11;		// reference thetapass/ThetaPassApplet.b0
					sconst_0;
					invokeinterface 3 67 4;		// javacard/security/AESKey
					getstatic_a 48;		// reference thetapass/ThetaPassApplet.randomData
					getfield_a_this 16;		// reference thetapass/ThetaPassApplet.fsIV
					sconst_0;
					bspush 16;
					invokevirtual 49;		// generateData([BSS)V
					getfield_a_this 11;		// reference thetapass/ThetaPassApplet.b0
					sconst_0;
					getfield_a_this 11;		// reference thetapass/ThetaPassApplet.b0
					arraylength;
					sconst_0;
					invokestatic 50;		// javacard/framework/Util.arrayFillNonAtomic([BSSB)S
					pop;
					aload_0;
					bspush 12;
					sspush 256;
					sconst_0;
					invokestatic 66;		// javacard/security/KeyBuilder.buildKey(BSZ)Ljavacard/security/Key;
					checkcast 0 69;		// T_CLASSORINTERFACE javacard/security/ECPrivateKey
					putfield_a 19;		// reference thetapass/ThetaPassApplet.privKey
					aload_0;
					bspush 11;
					sspush 256;
					sconst_0;
					invokestatic 66;		// javacard/security/KeyBuilder.buildKey(BSZ)Ljavacard/security/Key;
					checkcast 0 71;		// T_CLASSORINTERFACE javacard/security/ECPublicKey
					putfield_a 20;		// reference thetapass/ThetaPassApplet.pubKey
					getfield_a_this 19;		// reference thetapass/ThetaPassApplet.privKey
					invokestatic 73;		// thetapass/ECC.setCurveParameters(Ljavacard/security/ECKey;)V
					getfield_a_this 20;		// reference thetapass/ThetaPassApplet.pubKey
					invokestatic 73;		// thetapass/ECC.setCurveParameters(Ljavacard/security/ECKey;)V
					aload_0;
					new 74;		// javacard/security/KeyPair
					dup;
					getfield_a_this 20;		// reference thetapass/ThetaPassApplet.pubKey
					getfield_a_this 19;		// reference thetapass/ThetaPassApplet.privKey
					invokespecial 75;		// javacard/security/KeyPair.<init>(Ljavacard/security/PublicKey;Ljavacard/security/PrivateKey;)V
					putfield_a 21;		// reference thetapass/ThetaPassApplet.kp
					getfield_a_this 21;		// reference thetapass/ThetaPassApplet.kp
					invokevirtual 77;		// genKeyPair()V
					aload_0;
					sconst_3;
					sconst_0;
					invokestatic 78;		// javacard/security/KeyAgreement.getInstance(BZ)Ljavacard/security/KeyAgreement;
					putfield_a 7;		// reference thetapass/ThetaPassApplet.ecdh
					aload_0;
					invokevirtual 79;		// register()V
					return;
		}

		.method public uninstall()V 8 {
			.stack 1;
			.locals 0;

				L0:	getstatic_a 54;		// reference thetapass/ThetaPassApplet.api
					invokeinterface 1 56 2;		// KM101/T101OpenAPI
					pop;
					return;
		}

		.method private mainMenu(Ljavacard/framework/APDU;[B)V {
			.stack 9;
			.locals 8;

			.descriptor	Ljavacard/framework/APDU;	1.10;

				L0:	sconst_m1;
					sstore_3;
				L1:	sconst_0;
					sstore 4;
				L2:	sconst_0;
					sstore 5;
				L3:	sconst_0;
					sstore 6;
				L4:	sconst_0;
					sstore 7;
				L5:	bspush 64;
					sstore 8;
				L6:	sconst_0;
					sstore 9;
				L7:	sconst_0;
					sstore 10;
				L8:	getstatic_a 41;		// reference thetapass/ThetaPassApplet.apishim
					aload_2;
					invokevirtual 80;		// mainMenuUI([B)S
					sstore_3;
					sload_3;
					sconst_2;
					if_scmpeq L10;
				L9:	sspush 28497;
					invokestatic 68;		// javacard/framework/ISOException.throwIt(S)V
				L10:	aload_2;
					sconst_0;
					baload;
					sconst_1;
					if_scmpne_w L45;
				L11:	aload_2;
					sconst_1;
					baload;
					sspush 255;
					sand;
					sstore_3;
					sload_3;
					ifne L13;
				L12:	aload_0;
					sconst_2;
					getfield_a_this 11;		// reference thetapass/ThetaPassApplet.b0
					sconst_0;
					invokespecial 81;		// thetapass/ThetaPassApplet.listRecordLocIndexWithType(B[BS)S
					sstore 4;
					goto L21;
				L13:	sload_3;
					sconst_1;
					if_scmpne L15;
				L14:	aload_0;
					sconst_1;
					getfield_a_this 11;		// reference thetapass/ThetaPassApplet.b0
					sconst_0;
					invokespecial 81;		// thetapass/ThetaPassApplet.listRecordLocIndexWithType(B[BS)S
					sstore 4;
					goto L21;
				L15:	sload_3;
					sconst_2;
					if_scmpne L17;
				L16:	aload_0;
					sconst_3;
					getfield_a_this 11;		// reference thetapass/ThetaPassApplet.b0
					sconst_0;
					invokespecial 81;		// thetapass/ThetaPassApplet.listRecordLocIndexWithType(B[BS)S
					sstore 4;
					goto L21;
				L17:	sload_3;
					sconst_3;
					if_scmpne L19;
				L18:	aload_0;
					sconst_4;
					getfield_a_this 11;		// reference thetapass/ThetaPassApplet.b0
					sconst_0;
					invokespecial 81;		// thetapass/ThetaPassApplet.listRecordLocIndexWithType(B[BS)S
					sstore 4;
					goto L21;
				L19:	sload_3;
					sconst_4;
					if_scmpne L21;
				L20:	aload_0;
					sconst_5;
					getfield_a_this 11;		// reference thetapass/ThetaPassApplet.b0
					sconst_0;
					invokespecial 81;		// thetapass/ThetaPassApplet.listRecordLocIndexWithType(B[BS)S
					sstore 4;
				L21:	sload 4;
					ifle_w L44;
				L22:	sconst_1;
					sstore 10;
					goto_w L44;
				L23:	getfield_a_this 11;		// reference thetapass/ThetaPassApplet.b0
					sload 8;
					aload_0;
					aload_0;
					getfield_a_this 11;		// reference thetapass/ThetaPassApplet.b0
					sload 5;
					baload;
					invokespecial 85;		// thetapass/ThetaPassApplet.getRecordLocOffset(S)S
					getfield_a_this 11;		// reference thetapass/ThetaPassApplet.b0
					sload 8;
					sconst_1;
					sadd;
					invokespecial 89;		// thetapass/ThetaPassApplet.getEName0FromLocOff(S[BS)S
					sspush 255;
					sand;
					s2b;
					bastore;
					sload 8;
					getfield_a_this 11;		// reference thetapass/ThetaPassApplet.b0
					sload 8;
					baload;
					sspush 255;
					sand;
					sconst_1;
					sadd;
					sadd;
					sstore 8;
					sinc 7 1;
					sinc 5 1;
				L24:	sload 7;
					bspush 6;
					if_scmpge L26;
				L25:	sload 5;
					s2i;
					sload 4;
					s2i;
					iconst_1;
					isub;
					icmp;
					ifle L23;
				L26:	getstatic_a 41;		// reference thetapass/ThetaPassApplet.apishim
					getstatic_a 24;		// reference thetapass/APIShim.TXT_CRED_MENU_LIST
					getstatic_a 82;		// reference thetapass/APIShim.MENU_LIST_TITLE_OFF
					sload_3;
					saload;
					getstatic_a 83;		// reference thetapass/APIShim.MENU_LIST_TITLE_LEN
					sload_3;
					saload;
					sload 7;
					getfield_a_this 11;		// reference thetapass/ThetaPassApplet.b0
					bspush 64;
					sload 8;
					bspush 64;
					ssub;
					aload_2;
					invokevirtual 84;		// showScrollingList([BSSS[BSS[B)S
					sconst_2;
					if_scmpeq L28;
				L27:	sspush 28497;
					invokestatic 68;		// javacard/framework/ISOException.throwIt(S)V
				L28:	aload_2;
					sconst_0;
					baload;
					sconst_1;
					if_scmpne_w L35;
				L29:	sload 5;
					sload 7;
					ssub;
					aload_2;
					sconst_1;
					baload;
					sspush 255;
					sand;
					sadd;
					sstore 6;
					aload_0;
					aload_0;
					getfield_a_this 11;		// reference thetapass/ThetaPassApplet.b0
					sload 6;
					baload;
					invokespecial 85;		// thetapass/ThetaPassApplet.getRecordLocOffset(S)S
					getfield_a_this 11;		// reference thetapass/ThetaPassApplet.b0
					sspush 160;
					invokespecial 86;		// thetapass/ThetaPassApplet.getEName1FromLocOff(S[BS)S
					sstore 9;
					getstatic_a 41;		// reference thetapass/ThetaPassApplet.apishim
					getstatic_a 24;		// reference thetapass/APIShim.TXT_CRED_MENU_LIST
					getstatic_a 82;		// reference thetapass/APIShim.MENU_LIST_TITLE_OFF
					sload_3;
					saload;
					getstatic_a 83;		// reference thetapass/APIShim.MENU_LIST_TITLE_LEN
					sload_3;
					saload;
					getfield_a_this 11;		// reference thetapass/ThetaPassApplet.b0
					sspush 160;
					sload 9;
					aload_2;
					invokevirtual 87;		// confirmationUI([BSS[BSS[B)Z
					ifeq_w L43;
				L30:	getfield_a_this 15;		// reference thetapass/ThetaPassApplet.fs
					aload_0;
					getfield_a_this 11;		// reference thetapass/ThetaPassApplet.b0
					sload 6;
					baload;
					invokespecial 85;		// thetapass/ThetaPassApplet.getRecordLocOffset(S)S
					sconst_3;
					sadd;
					baload;
					sspush 255;
					sand;
					sstore 9;
					aload_0;
					sconst_1;
					getfield_a_this 11;		// reference thetapass/ThetaPassApplet.b0
					sload 6;
					baload;
					getfield_a_this 11;		// reference thetapass/ThetaPassApplet.b0
					sspush 160;
					aload_2;
					sconst_0;
					invokespecial 88;		// thetapass/ThetaPassApplet.cryptoContent(BS[BS[BS)Z
					ifne L32;
				L31:	sspush 27013;
					invokestatic 68;		// javacard/framework/ISOException.throwIt(S)V
				L32:	getstatic_a 41;		// reference thetapass/ThetaPassApplet.apishim
					getstatic_a 24;		// reference thetapass/APIShim.TXT_CRED_MENU_LIST
					getstatic_a 82;		// reference thetapass/APIShim.MENU_LIST_TITLE_OFF
					sload_3;
					saload;
					getstatic_a 83;		// reference thetapass/APIShim.MENU_LIST_TITLE_LEN
					sload_3;
					saload;
					getfield_a_this 11;		// reference thetapass/ThetaPassApplet.b0
					sspush 160;
					sload 9;
					aload_2;
					invokevirtual 87;		// confirmationUI([BSS[BSS[B)Z
					pop;
					sload 5;
					bspush 6;
					if_scmpgt L34;
				L33:	sconst_0;
					sstore 5;
					goto L43;
				L34:	sload 5;
					sload 7;
					bspush 6;
					sadd;
					ssub;
					sstore 5;
					goto L43;
				L35:	aload_2;
					sconst_0;
					baload;
					sconst_2;
					if_scmpne L37;
				L36:	goto L45;
				L37:	aload_2;
					sconst_0;
					baload;
					sconst_3;
					if_scmpne L43;
				L38:	aload_2;
					sconst_1;
					baload;
					bspush -2;
					if_scmpne L43;
				L39:	sload 5;
					sload 7;
					ssub;
					bspush 6;
					ssub;
					sload 4;
					sconst_1;
					ssub;
					if_scmpgt L43;
				L40:	sload 5;
					bspush 6;
					if_scmpgt L42;
				L41:	sconst_0;
					sstore 5;
					goto L43;
				L42:	sload 5;
					sload 7;
					bspush 6;
					sadd;
					ssub;
					sstore 5;
				L43:	sconst_0;
					sstore 7;
					bspush 64;
					sstore 8;
				L44:	sload 10;
					ifne_w L24;
				L45:	return;
		}

		.method private secureChannel(Ljavacard/framework/APDU;[B)V {
			.stack 8;
			.locals 3;

			.descriptor	Ljavacard/framework/APDU;	1.10;

				L0:	getfield_a_this 14;		// reference thetapass/ThetaPassApplet.sb
					sconst_0;
					aload_1;
					invokevirtual 90;		// setIncomingAndReceive()S
					sastore;
					getfield_a_this 14;		// reference thetapass/ThetaPassApplet.sb
					sconst_0;
					saload;
					bspush 65;
					if_scmpne_w L10;
				L1:	getfield_a_this 11;		// reference thetapass/ThetaPassApplet.b0
					sconst_0;
					getfield_a_this 11;		// reference thetapass/ThetaPassApplet.b0
					arraylength;
					sconst_0;
					invokestatic 50;		// javacard/framework/Util.arrayFillNonAtomic([BSSB)S
					pop;
					getfield_a_this 13;		// reference thetapass/ThetaPassApplet.b2
					sconst_0;
					getfield_a_this 13;		// reference thetapass/ThetaPassApplet.b2
					arraylength;
					sconst_0;
					invokestatic 50;		// javacard/framework/Util.arrayFillNonAtomic([BSSB)S
					pop;
					getfield_a_this 8;		// reference thetapass/ThetaPassApplet.md
					invokevirtual 91;		// reset()V
					getfield_a_this 8;		// reference thetapass/ThetaPassApplet.md
					aload_2;
					sconst_5;
					bspush 65;
					invokevirtual 92;		// update([BSS)V
					getfield_a_this 20;		// reference thetapass/ThetaPassApplet.pubKey
					getfield_a_this 11;		// reference thetapass/ThetaPassApplet.b0
					sconst_0;
					invokeinterface 3 71 19;		// javacard/security/ECPublicKey
					pop;
					getfield_a_this 8;		// reference thetapass/ThetaPassApplet.md
					getfield_a_this 11;		// reference thetapass/ThetaPassApplet.b0
					sconst_0;
					bspush 65;
					getfield_a_this 11;		// reference thetapass/ThetaPassApplet.b0
					bspush 65;
					invokevirtual 93;		// doFinal([BSS[BS)S
					pop;
					getfield_a_this 11;		// reference thetapass/ThetaPassApplet.b0
					bspush 65;
					getfield_a_this 13;		// reference thetapass/ThetaPassApplet.b2
					sconst_0;
					bspush 12;
					invokestatic 51;		// javacard/framework/Util.arrayCopyNonAtomic([BS[BSS)S
					pop;
					getfield_a_this 7;		// reference thetapass/ThetaPassApplet.ecdh
					getfield_a_this 19;		// reference thetapass/ThetaPassApplet.privKey
					invokevirtual 94;		// init(Ljavacard/security/PrivateKey;)V
				L2:	getfield_a_this 7;		// reference thetapass/ThetaPassApplet.ecdh
					aload_2;
					sconst_5;
					bspush 65;
					getfield_a_this 11;		// reference thetapass/ThetaPassApplet.b0
					sconst_0;
					invokevirtual 95;		// generateSecret([BSS[BS)S
					pop;
				L3:	goto L6;
				L4:	astore_3;
				L5:	sspush 28621;
					invokestatic 68;		// javacard/framework/ISOException.throwIt(S)V
				L6:	getfield_a_this 8;		// reference thetapass/ThetaPassApplet.md
					invokevirtual 91;		// reset()V
					getfield_a_this 8;		// reference thetapass/ThetaPassApplet.md
					getfield_a_this 11;		// reference thetapass/ThetaPassApplet.b0
					sconst_0;
					bspush 32;
					getfield_a_this 11;		// reference thetapass/ThetaPassApplet.b0
					sconst_0;
					invokevirtual 93;		// doFinal([BSS[BS)S
					pop;
					getfield_a_this 10;		// reference thetapass/ThetaPassApplet.sessKey
					getfield_a_this 11;		// reference thetapass/ThetaPassApplet.b0
					sconst_0;
					invokeinterface 3 67 4;		// javacard/security/AESKey
					getfield_a_this 8;		// reference thetapass/ThetaPassApplet.md
					invokevirtual 91;		// reset()V
					getfield_a_this 8;		// reference thetapass/ThetaPassApplet.md
					getfield_a_this 11;		// reference thetapass/ThetaPassApplet.b0
					sconst_0;
					bspush 32;
					getfield_a_this 11;		// reference thetapass/ThetaPassApplet.b0
					sconst_0;
					invokevirtual 93;		// doFinal([BSS[BS)S
					pop;
					getfield_a_this 11;		// reference thetapass/ThetaPassApplet.b0
					bspush 31;
					baload;
					bspush 15;
					sand;
					sstore_3;
				L7:	getfield_a_this 11;		// reference thetapass/ThetaPassApplet.b0
					sload_3;
					baload;
					s2i;
					bipush 127;
					iand;
					bipush 24;
					ishl;
					getfield_a_this 11;		// reference thetapass/ThetaPassApplet.b0
					sload_3;
					sconst_1;
					sadd;
					baload;
					s2i;
					sipush 255;
					iand;
					bipush 16;
					ishl;
					ior;
					getfield_a_this 11;		// reference thetapass/ThetaPassApplet.b0
					sload_3;
					sconst_2;
					sadd;
					baload;
					s2i;
					sipush 255;
					iand;
					bipush 8;
					ishl;
					ior;
					getfield_a_this 11;		// reference thetapass/ThetaPassApplet.b0
					sload_3;
					sconst_3;
					sadd;
					baload;
					s2i;
					sipush 255;
					iand;
					ior;
					istore 4;
				L8:	iload 4;
					iipush 1000000;
					irem;
					getfield_a_this 11;		// reference thetapass/ThetaPassApplet.b0
					sconst_0;
					invokestatic 96;		// thetapass/Codec.intToBytes(I[BS)V
					getfield_a_this 14;		// reference thetapass/ThetaPassApplet.sb
					sconst_0;
					getfield_a_this 11;		// reference thetapass/ThetaPassApplet.b0
					sconst_0;
					sconst_4;
					aload_2;
					sconst_0;
					invokestatic 97;		// thetapass/Codec.toDecimalASCII([BSS[BS)S
					sastore;
					aload_2;
					sconst_4;
					getfield_a_this 11;		// reference thetapass/ThetaPassApplet.b0
					bspush 96;
					bspush 6;
					invokestatic 51;		// javacard/framework/Util.arrayCopyNonAtomic([BS[BSS)S
					pop;
					getfield_a_this 11;		// reference thetapass/ThetaPassApplet.b0
					sconst_0;
					bspush 96;
					bspush 32;
					invokestatic 50;		// javacard/framework/Util.arrayFillNonAtomic([BSSB)S
					pop;
					getstatic_a 98;		// reference thetapass/APIShim.TXT_CCODE
					sconst_0;
					getfield_a_this 11;		// reference thetapass/ThetaPassApplet.b0
					sconst_0;
					getstatic_a 98;		// reference thetapass/APIShim.TXT_CCODE
					arraylength;
					invokestatic 51;		// javacard/framework/Util.arrayCopyNonAtomic([BS[BSS)S
					pop;
					getfield_a_this 11;		// reference thetapass/ThetaPassApplet.b0
					getstatic_a 98;		// reference thetapass/APIShim.TXT_CCODE
					arraylength;
					bspush 58;
					bastore;
					getfield_a_this 11;		// reference thetapass/ThetaPassApplet.b0
					bspush 96;
					getfield_a_this 11;		// reference thetapass/ThetaPassApplet.b0
					bspush 16;
					bspush 6;
					invokestatic 51;		// javacard/framework/Util.arrayCopyNonAtomic([BS[BSS)S
					pop;
					getstatic_a 99;		// reference thetapass/APIShim.TXT_PROMPT_OKC
					sconst_0;
					getfield_a_this 11;		// reference thetapass/ThetaPassApplet.b0
					bspush 80;
					getstatic_a 99;		// reference thetapass/APIShim.TXT_PROMPT_OKC
					arraylength;
					invokestatic 51;		// javacard/framework/Util.arrayCopyNonAtomic([BS[BSS)S
					pop;
					getstatic_a 41;		// reference thetapass/ThetaPassApplet.apishim
					getstatic_a 100;		// reference thetapass/APIShim.TXT_SECURE_SESS
					sconst_0;
					getstatic_a 100;		// reference thetapass/APIShim.TXT_SECURE_SESS
					arraylength;
					getfield_a_this 11;		// reference thetapass/ThetaPassApplet.b0
					sconst_0;
					bspush 96;
					aload_2;
					invokevirtual 87;		// confirmationUI([BSS[BSS[B)Z
					pop;
				L9:	goto L11;
				L10:	sspush 26368;
					invokestatic 68;		// javacard/framework/ISOException.throwIt(S)V
				L11:	return;
			.exceptionTable {
				// start_block end_block handler_block catch_type_index
				L2 L3 L4 34;
			}
		}

		.method private securePacketProcess(B[BSS[BSSS[B)S {
			.stack 16;
			.locals 0;

				L0:	getfield_a_this 10;		// reference thetapass/ThetaPassApplet.sessKey
					invokeinterface 1 67 3;		// javacard/security/AESKey
					ifeq_w L11;
				L1:	getfield_a_this 13;		// reference thetapass/ThetaPassApplet.b2
					bspush 12;
					baload;
					getfield_a_this 13;		// reference thetapass/ThetaPassApplet.b2
					bspush 13;
					baload;
					invokestatic 64;		// javacard/framework/Util.makeShort(BB)S
					s2i;
					iipush 65535;
					icmp;
					ifge_w L11;
				L2:	getfield_a_this 13;		// reference thetapass/ThetaPassApplet.b2
					bspush 14;
					baload;
					getfield_a_this 13;		// reference thetapass/ThetaPassApplet.b2
					bspush 15;
					baload;
					invokestatic 64;		// javacard/framework/Util.makeShort(BB)S
					s2i;
					iipush 65535;
					icmp;
					ifge_w L11;
				L3:	sload_1;
					sconst_2;
					if_scmpne_w L6;
				L4:	sload 7;
					sspush 200;
					if_scmpgt_w L6;
				L5:	getfield_a_this 8;		// reference thetapass/ThetaPassApplet.md
					invokevirtual 91;		// reset()V
					getfield_a_this 8;		// reference thetapass/ThetaPassApplet.md
					getfield_a_this 13;		// reference thetapass/ThetaPassApplet.b2
					sconst_0;
					getfield_a_this 13;		// reference thetapass/ThetaPassApplet.b2
					arraylength;
					aload 9;
					sconst_0;
					invokevirtual 93;		// doFinal([BSS[BS)S
					pop;
					getfield_a_this 5;		// reference thetapass/ThetaPassApplet.cipher
					getfield_a_this 10;		// reference thetapass/ThetaPassApplet.sessKey
					sload_1;
					aload 9;
					sconst_0;
					bspush 16;
					invokevirtual 101;		// init(Ljavacard/security/Key;B[BSS)V
					getfield_a_this 5;		// reference thetapass/ThetaPassApplet.cipher
					aload 5;
					sload 6;
					sload 7;
					aload 9;
					bspush 16;
					invokevirtual 102;		// doFinal([BSS[BS)S
					sstore 8;
					getfield_a_this 8;		// reference thetapass/ThetaPassApplet.md
					invokevirtual 91;		// reset()V
					getfield_a_this 8;		// reference thetapass/ThetaPassApplet.md
					aload_2;
					sload_3;
					sload 4;
					invokevirtual 92;		// update([BSS)V
					getfield_a_this 8;		// reference thetapass/ThetaPassApplet.md
					aload 9;
					sconst_0;
					bspush 16;
					sload 8;
					sadd;
					aload 9;
					bspush 16;
					sload 8;
					sadd;
					invokevirtual 93;		// doFinal([BSS[BS)S
					pop;
					aload 9;
					bspush 16;
					getfield_a_this 11;		// reference thetapass/ThetaPassApplet.b0
					sconst_0;
					bspush 32;
					sload 8;
					sadd;
					invokestatic 51;		// javacard/framework/Util.arrayCopyNonAtomic([BS[BSS)S
					pop;
					getfield_a_this 10;		// reference thetapass/ThetaPassApplet.sessKey
					aload 9;
					sconst_0;
					invokeinterface 3 67 5;		// javacard/security/AESKey
					pop;
					getfield_a_this 11;		// reference thetapass/ThetaPassApplet.b0
					sload 8;
					aload 9;
					bspush 32;
					bspush 32;
					invokestatic 51;		// javacard/framework/Util.arrayCopyNonAtomic([BS[BSS)S
					pop;
					getstatic_a 54;		// reference thetapass/ThetaPassApplet.api
					sconst_4;
					aload 9;
					sconst_0;
					bspush 32;
					aload 9;
					bspush 32;
					bspush 32;
					aload 9;
					bspush 64;
					aload 9;
					sspush 128;
					aload 9;
					sspush 192;
					aload 9;
					sconst_0;
					invokeinterface 16 56 23;		// KM101/T101OpenAPI
					pop;
					aload 9;
					sconst_0;
					getfield_a_this 11;		// reference thetapass/ThetaPassApplet.b0
					sload 8;
					bspush 32;
					invokestatic 51;		// javacard/framework/Util.arrayCopyNonAtomic([BS[BSS)S
					pop;
					getfield_a_this 11;		// reference thetapass/ThetaPassApplet.b0
					sconst_0;
					aload 9;
					sconst_0;
					bspush 32;
					sload 8;
					sadd;
					invokestatic 51;		// javacard/framework/Util.arrayCopyNonAtomic([BS[BSS)S
					pop;
					getfield_a_this 13;		// reference thetapass/ThetaPassApplet.b2
					bspush 14;
					baload;
					getfield_a_this 13;		// reference thetapass/ThetaPassApplet.b2
					bspush 15;
					baload;
					invokestatic 64;		// javacard/framework/Util.makeShort(BB)S
					sconst_1;
					sadd;
					getfield_a_this 13;		// reference thetapass/ThetaPassApplet.b2
					bspush 14;
					invokestatic 103;		// thetapass/Codec.shortToBytes(S[BS)V
					sload 8;
					bspush 32;
					sadd;
					sreturn;
				L6:	sload_1;
					sconst_1;
					if_scmpne_w L12;
				L7:	sload 7;
					sspush 240;
					if_scmpgt_w L12;
				L8:	getfield_a_this 8;		// reference thetapass/ThetaPassApplet.md
					invokevirtual 91;		// reset()V
					getfield_a_this 8;		// reference thetapass/ThetaPassApplet.md
					getfield_a_this 13;		// reference thetapass/ThetaPassApplet.b2
					sconst_0;
					getfield_a_this 13;		// reference thetapass/ThetaPassApplet.b2
					arraylength;
					aload 9;
					sconst_0;
					invokevirtual 93;		// doFinal([BSS[BS)S
					pop;
					getfield_a_this 8;		// reference thetapass/ThetaPassApplet.md
					invokevirtual 91;		// reset()V
					getfield_a_this 8;		// reference thetapass/ThetaPassApplet.md
					aload_2;
					sload_3;
					sload 4;
					invokevirtual 92;		// update([BSS)V
					getfield_a_this 8;		// reference thetapass/ThetaPassApplet.md
					aload 9;
					sconst_0;
					bspush 16;
					invokevirtual 92;		// update([BSS)V
					getfield_a_this 8;		// reference thetapass/ThetaPassApplet.md
					aload 5;
					sload 6;
					sload 7;
					bspush 32;
					ssub;
					aload 9;
					bspush 32;
					invokevirtual 93;		// doFinal([BSS[BS)S
					pop;
					getfield_a_this 10;		// reference thetapass/ThetaPassApplet.sessKey
					aload 9;
					sconst_0;
					invokeinterface 3 67 5;		// javacard/security/AESKey
					pop;
					getstatic_a 54;		// reference thetapass/ThetaPassApplet.api
					sconst_4;
					aload 9;
					sconst_0;
					bspush 32;
					aload 9;
					bspush 32;
					bspush 32;
					aload 9;
					bspush 64;
					aload 9;
					sspush 128;
					aload 9;
					sspush 192;
					aload 9;
					sspush 192;
					invokeinterface 16 56 23;		// KM101/T101OpenAPI
					pop;
					aload 5;
					sload 7;
					bspush 32;
					ssub;
					aload 9;
					sspush 192;
					bspush 32;
					invokestatic 33;		// javacard/framework/Util.arrayCompare([BS[BSS)B
					ifne L10;
				L9:	getfield_a_this 8;		// reference thetapass/ThetaPassApplet.md
					invokevirtual 91;		// reset()V
					getfield_a_this 8;		// reference thetapass/ThetaPassApplet.md
					getfield_a_this 13;		// reference thetapass/ThetaPassApplet.b2
					sconst_0;
					getfield_a_this 13;		// reference thetapass/ThetaPassApplet.b2
					arraylength;
					aload 9;
					sconst_0;
					invokevirtual 93;		// doFinal([BSS[BS)S
					pop;
					getfield_a_this 5;		// reference thetapass/ThetaPassApplet.cipher
					getfield_a_this 10;		// reference thetapass/ThetaPassApplet.sessKey
					sload_1;
					aload 9;
					sconst_0;
					bspush 16;
					invokevirtual 101;		// init(Ljavacard/security/Key;B[BSS)V
					getfield_a_this 5;		// reference thetapass/ThetaPassApplet.cipher
					aload 5;
					sload 6;
					sload 7;
					bspush 32;
					ssub;
					aload 9;
					sconst_0;
					invokevirtual 102;		// doFinal([BSS[BS)S
					sstore 8;
					getfield_a_this 13;		// reference thetapass/ThetaPassApplet.b2
					bspush 12;
					baload;
					getfield_a_this 13;		// reference thetapass/ThetaPassApplet.b2
					bspush 13;
					baload;
					invokestatic 64;		// javacard/framework/Util.makeShort(BB)S
					sconst_1;
					sadd;
					getfield_a_this 13;		// reference thetapass/ThetaPassApplet.b2
					bspush 12;
					invokestatic 103;		// thetapass/Codec.shortToBytes(S[BS)V
					sload 8;
					sreturn;
				L10:	sspush 27010;
					invokestatic 68;		// javacard/framework/ISOException.throwIt(S)V
					goto L12;
				L11:	sspush 28620;
					invokestatic 68;		// javacard/framework/ISOException.throwIt(S)V
				L12:	sconst_m1;
					sreturn;
		}

		.method private fsGet(Ljavacard/framework/APDU;[B)V {
			.stack 7;
			.locals 3;

			.descriptor	Ljavacard/framework/APDU;	1.10;

				L0:	aload_2;
					sconst_2;
					baload;
					ifne L3;
				L1:	aload_2;
					sconst_3;
					baload;
					ifne L3;
				L2:	aload_2;
					sconst_0;
					aload_0;
					invokespecial 104;		// thetapass/ThetaPassApplet.countFreeRecords()S
					invokestatic 105;		// javacard/framework/Util.setShort([BSS)S
					pop;
					aload_2;
					sconst_2;
					aload_0;
					invokespecial 106;		// thetapass/ThetaPassApplet.countTotalRecords()S
					invokestatic 105;		// javacard/framework/Util.setShort([BSS)S
					pop;
					aload_1;
					sconst_0;
					sconst_4;
					invokevirtual 107;		// setOutgoingAndSend(SS)V
					goto_w L40;
				L3:	aload_2;
					sconst_2;
					baload;
					sconst_1;
					if_scmpeq L9;
				L4:	aload_2;
					sconst_2;
					baload;
					sconst_2;
					if_scmpeq L9;
				L5:	aload_2;
					sconst_2;
					baload;
					sconst_3;
					if_scmpeq L9;
				L6:	aload_2;
					sconst_2;
					baload;
					sconst_4;
					if_scmpeq L9;
				L7:	aload_2;
					sconst_2;
					baload;
					sconst_5;
					if_scmpeq L9;
				L8:	aload_2;
					sconst_2;
					baload;
					bspush 6;
					if_scmpne_w L39;
				L9:	aload_2;
					sconst_3;
					baload;
					ifne L11;
				L10:	aload_2;
					sconst_0;
					aload_0;
					aload_2;
					sconst_2;
					baload;
					invokespecial 108;		// thetapass/ThetaPassApplet.countRecordByType(B)S
					invokestatic 105;		// javacard/framework/Util.setShort([BSS)S
					pop;
					aload_1;
					sconst_0;
					sconst_2;
					invokevirtual 107;		// setOutgoingAndSend(SS)V
					goto_w L40;
				L11:	aload_2;
					sconst_3;
					baload;
					sconst_1;
					if_scmpne L24;
				L12:	getfield_a_this 14;		// reference thetapass/ThetaPassApplet.sb
					sconst_0;
					aload_1;
					invokevirtual 90;		// setIncomingAndReceive()S
					sastore;
					getfield_a_this 14;		// reference thetapass/ThetaPassApplet.sb
					sconst_0;
					saload;
					sconst_4;
					if_scmpeq L14;
				L13:	sspush 26368;
					invokestatic 68;		// javacard/framework/ISOException.throwIt(S)V
				L14:	aload_2;
					sconst_5;
					baload;
					aload_2;
					bspush 6;
					baload;
					invokestatic 64;		// javacard/framework/Util.makeShort(BB)S
					sstore_3;
				L15:	aload_2;
					bspush 7;
					baload;
					aload_2;
					bspush 8;
					baload;
					invokestatic 64;		// javacard/framework/Util.makeShort(BB)S
					sstore 4;
				L16:	sload_3;
					bspush 64;
					if_scmpgt L18;
				L17:	sload 4;
					bspush 6;
					if_scmple L19;
				L18:	sspush 27392;
					invokestatic 68;		// javacard/framework/ISOException.throwIt(S)V
				L19:	aload_0;
					aload_2;
					sconst_2;
					baload;
					sload_3;
					sload 4;
					aload_2;
					sconst_0;
					invokespecial 109;		// thetapass/ThetaPassApplet.getRecordEName0List(BSS[BS)S
					sstore 5;
				L20:	sload 5;
					sconst_m1;
					if_scmpne L22;
				L21:	sspush 27013;
					invokestatic 68;		// javacard/framework/ISOException.throwIt(S)V
				L22:	aload_1;
					sconst_0;
					sload 5;
					invokevirtual 107;		// setOutgoingAndSend(SS)V
				L23:	goto_w L40;
				L24:	aload_2;
					sconst_3;
					baload;
					sconst_2;
					if_scmpne L32;
				L25:	getfield_a_this 14;		// reference thetapass/ThetaPassApplet.sb
					sconst_0;
					aload_1;
					invokevirtual 90;		// setIncomingAndReceive()S
					sastore;
					sconst_m1;
					sstore_3;
				L26:	aload_0;
					aload_2;
					sconst_2;
					baload;
					aload_2;
					aload_1;
					invokevirtual 110;		// getOffsetCdata()S
					getfield_a_this 14;		// reference thetapass/ThetaPassApplet.sb
					sconst_0;
					saload;
					invokespecial 111;		// thetapass/ThetaPassApplet.searchRecordLocWithEName0AndType(B[BSS)S
					sstore_3;
					sload_3;
					sconst_m1;
					if_scmpne L28;
				L27:	sspush 27267;
					invokestatic 68;		// javacard/framework/ISOException.throwIt(S)V
				L28:	getfield_a_this 14;		// reference thetapass/ThetaPassApplet.sb
					sconst_0;
					getfield_a_this 15;		// reference thetapass/ThetaPassApplet.fs
					aload_0;
					sload_3;
					invokespecial 85;		// thetapass/ThetaPassApplet.getRecordLocOffset(S)S
					sconst_3;
					sadd;
					baload;
					sspush 255;
					sand;
					sastore;
					aload_0;
					sconst_1;
					sload_3;
					aload_2;
					sconst_0;
					getfield_a_this 11;		// reference thetapass/ThetaPassApplet.b0
					sconst_0;
					invokespecial 88;		// thetapass/ThetaPassApplet.cryptoContent(BS[BS[BS)Z
					ifne L30;
				L29:	sspush 27013;
					invokestatic 68;		// javacard/framework/ISOException.throwIt(S)V
				L30:	aload_1;
					sconst_0;
					getfield_a_this 14;		// reference thetapass/ThetaPassApplet.sb
					sconst_0;
					saload;
					invokevirtual 107;		// setOutgoingAndSend(SS)V
				L31:	goto L40;
				L32:	aload_2;
					sconst_3;
					baload;
					sconst_3;
					if_scmpne L38;
				L33:	getfield_a_this 14;		// reference thetapass/ThetaPassApplet.sb
					sconst_0;
					aload_1;
					invokevirtual 90;		// setIncomingAndReceive()S
					sastore;
					aload_0;
					aload_2;
					sconst_2;
					baload;
					aload_2;
					aload_1;
					invokevirtual 110;		// getOffsetCdata()S
					getfield_a_this 14;		// reference thetapass/ThetaPassApplet.sb
					sconst_0;
					saload;
					invokespecial 111;		// thetapass/ThetaPassApplet.searchRecordLocWithEName0AndType(B[BSS)S
					sstore_3;
				L34:	sload_3;
					sconst_m1;
					if_scmpne L36;
				L35:	sspush 27267;
					invokestatic 68;		// javacard/framework/ISOException.throwIt(S)V
				L36:	getfield_a_this 14;		// reference thetapass/ThetaPassApplet.sb
					sconst_0;
					aload_0;
					aload_0;
					sload_3;
					invokespecial 85;		// thetapass/ThetaPassApplet.getRecordLocOffset(S)S
					aload_2;
					sconst_0;
					invokespecial 86;		// thetapass/ThetaPassApplet.getEName1FromLocOff(S[BS)S
					sastore;
					aload_1;
					sconst_0;
					getfield_a_this 14;		// reference thetapass/ThetaPassApplet.sb
					sconst_0;
					saload;
					invokevirtual 107;		// setOutgoingAndSend(SS)V
				L37:	goto L40;
				L38:	sspush 27392;
					invokestatic 68;		// javacard/framework/ISOException.throwIt(S)V
					goto L40;
				L39:	sspush 27392;
					invokestatic 68;		// javacard/framework/ISOException.throwIt(S)V
				L40:	return;
		}

		.method private fsPut(Ljavacard/framework/APDU;[B)V {
			.stack 13;
			.locals 4;

			.descriptor	Ljavacard/framework/APDU;	1.10;

				L0:	getfield_a_this 14;		// reference thetapass/ThetaPassApplet.sb
					sconst_0;
					aload_1;
					invokevirtual 90;		// setIncomingAndReceive()S
					sastore;
					aload_2;
					sconst_2;
					baload;
					sstore_3;
				L1:	sload_3;
					sconst_1;
					if_scmpeq L7;
				L2:	aload_2;
					sconst_2;
					baload;
					sconst_2;
					if_scmpeq L7;
				L3:	sload_3;
					sconst_3;
					if_scmpeq L7;
				L4:	sload_3;
					sconst_4;
					if_scmpeq L7;
				L5:	sload_3;
					sconst_5;
					if_scmpeq L7;
				L6:	sload_3;
					bspush 6;
					if_scmpne_w L32;
				L7:	aload_2;
					sconst_5;
					baload;
					sspush 255;
					sand;
					sstore 4;
				L8:	aload_2;
					bspush 6;
					baload;
					sspush 255;
					sand;
					sstore 5;
				L9:	aload_2;
					bspush 7;
					baload;
					sspush 255;
					sand;
					sstore 6;
				L10:	sload 4;
					bspush 15;
					if_scmple L12;
				L11:	sspush 26368;
					invokestatic 68;		// javacard/framework/ISOException.throwIt(S)V
				L12:	aload_2;
					bspush 8;
					sload 4;
					sconst_0;
					invokestatic 112;		// thetapass/Codec.isInputAllowable([BSSZ)Z
					ifne L14;
				L13:	sspush 27012;
					invokestatic 68;		// javacard/framework/ISOException.throwIt(S)V
				L14:	sload_3;
					sconst_5;
					if_scmpne L18;
				L15:	sload 5;
					sconst_4;
					if_scmpne L17;
				L16:	sload 6;
					bspush 80;
					if_scmple L21;
				L17:	sspush 26368;
					invokestatic 68;		// javacard/framework/ISOException.throwIt(S)V
					goto L21;
				L18:	sload 5;
					bspush 48;
					if_scmpgt L20;
				L19:	sload 6;
					bspush 80;
					if_scmple L21;
				L20:	sspush 26368;
					invokestatic 68;		// javacard/framework/ISOException.throwIt(S)V
				L21:	sload_3;
					sconst_1;
					if_scmpne L24;
				L22:	aload_2;
					bspush 8;
					sload 4;
					sadd;
					sload 5;
					sconst_1;
					invokestatic 112;		// thetapass/Codec.isInputAllowable([BSSZ)Z
					ifne L29;
				L23:	sspush 27012;
					invokestatic 68;		// javacard/framework/ISOException.throwIt(S)V
					goto L29;
				L24:	sload_3;
					sconst_5;
					if_scmpne L27;
				L25:	aload_2;
					bspush 8;
					sload 4;
					sadd;
					sload 5;
					sadd;
					sload 6;
					sconst_1;
					invokestatic 112;		// thetapass/Codec.isInputAllowable([BSSZ)Z
					ifne L29;
				L26:	sspush 27012;
					invokestatic 68;		// javacard/framework/ISOException.throwIt(S)V
					goto L29;
				L27:	aload_2;
					bspush 8;
					sload 4;
					sadd;
					sload 5;
					sload 6;
					sadd;
					sconst_1;
					invokestatic 112;		// thetapass/Codec.isInputAllowable([BSSZ)Z
					ifne L29;
				L28:	sspush 27012;
					invokestatic 68;		// javacard/framework/ISOException.throwIt(S)V
				L29:	aload_0;
					sload_3;
					aload_2;
					bspush 8;
					sload 4;
					aload_2;
					bspush 8;
					sload 4;
					sadd;
					sload 5;
					aload_2;
					bspush 8;
					sload 4;
					sadd;
					sload 5;
					sadd;
					sload 6;
					getfield_a_this 11;		// reference thetapass/ThetaPassApplet.b0
					sconst_0;
					invokespecial 113;		// thetapass/ThetaPassApplet.setRecord(B[BSS[BSS[BSS[BS)Z
					ifne L33;
				L30:	sspush 28465;
					invokestatic 68;		// javacard/framework/ISOException.throwIt(S)V
				L31:	goto L33;
				L32:	sspush 27392;
					invokestatic 68;		// javacard/framework/ISOException.throwIt(S)V
				L33:	return;
		}

		.method private isActiveFromFlag(B)Z {
			.stack 2;
			.locals 0;

				L0:	sload_1;
					bspush -128;
					sand;
					bspush 7;
					sshr;
					sconst_1;
					if_scmpne L2;
				L1:	sconst_1;
					sreturn;
				L2:	sconst_0;
					sreturn;
		}

		.method private isAuthNeededFromFlag(B)Z {
			.stack 2;
			.locals 0;

				L0:	sload_1;
					bspush 64;
					sand;
					bspush 6;
					sshr;
					sconst_1;
					if_scmpne L2;
				L1:	sconst_1;
					sreturn;
				L2:	sconst_0;
					sreturn;
		}

		.method private isHiddenTillAuthFromFlag(B)Z {
			.stack 2;
			.locals 0;

				L0:	sload_1;
					bspush 32;
					sand;
					sconst_5;
					sshr;
					sconst_1;
					if_scmpne L3;
				L1:	aload_0;
					sload_1;
					invokespecial 114;		// thetapass/ThetaPassApplet.isAuthNeededFromFlag(B)Z
					ifeq L3;
				L2:	sconst_1;
					sreturn;
				L3:	sconst_0;
					sreturn;
		}

		.method private getTypeFromFlag(B)B {
			.stack 2;
			.locals 0;

				L0:	sload_1;
					bspush 15;
					sand;
					sreturn;
		}

		.method private getRecordLocOffset(S)S {
			.stack 2;
			.locals 0;

				L0:	sload_1;
					sspush 147;
					smul;
					sreturn;
		}

		.method private countTotalRecords()S {
			.stack 3;
			.locals 2;

				L0:	sconst_0;
					sstore_1;
				L1:	sconst_0;
					sstore_2;
				L2:	goto L6;
				L3:	getfield_a_this 15;		// reference thetapass/ThetaPassApplet.fs
					aload_0;
					sload_2;
					invokespecial 85;		// thetapass/ThetaPassApplet.getRecordLocOffset(S)S
					sconst_0;
					sadd;
					baload;
					ifeq L5;
				L4:	sinc 1 1;
				L5:	sinc 2 1;
				L6:	sload_2;
					bspush 64;
					if_scmplt L3;
				L7:	sload_1;
					sreturn;
		}

		.method private countFreeRecords()S {
			.stack 2;
			.locals 0;

				L0:	bspush 64;
					aload_0;
					invokespecial 106;		// thetapass/ThetaPassApplet.countTotalRecords()S
					ssub;
					sreturn;
		}

		.method private countRecordByType(B)S {
			.stack 4;
			.locals 2;

				L0:	sconst_0;
					sstore_2;
				L1:	sconst_0;
					sstore_3;
				L2:	goto L6;
				L3:	aload_0;
					getfield_a_this 15;		// reference thetapass/ThetaPassApplet.fs
					aload_0;
					sload_3;
					invokespecial 85;		// thetapass/ThetaPassApplet.getRecordLocOffset(S)S
					sconst_0;
					sadd;
					baload;
					invokespecial 115;		// thetapass/ThetaPassApplet.getTypeFromFlag(B)B
					sload_1;
					if_scmpne L5;
				L4:	sinc 2 1;
				L5:	sinc 3 1;
				L6:	sload_3;
					bspush 64;
					if_scmplt L3;
				L7:	sload_2;
					sreturn;
		}

		.method private searchRecordLocOffsetWithEName0AndType(B[BSS)S {
			.stack 5;
			.locals 4;

				L0:	sconst_0;
					sstore 8;
				L1:	goto L10;
				L2:	aload_0;
					sload 8;
					invokespecial 85;		// thetapass/ThetaPassApplet.getRecordLocOffset(S)S
					sstore 6;
				L3:	aload_0;
					getfield_a_this 15;		// reference thetapass/ThetaPassApplet.fs
					sload 6;
					sconst_0;
					sadd;
					baload;
					invokespecial 115;		// thetapass/ThetaPassApplet.getTypeFromFlag(B)B
					sstore 5;
				L4:	getfield_a_this 15;		// reference thetapass/ThetaPassApplet.fs
					sload 6;
					sconst_1;
					sadd;
					baload;
					sspush 255;
					sand;
					sstore 7;
				L5:	sload 5;
					sload_1;
					if_scmpne L9;
				L6:	sload 7;
					sload 4;
					if_scmpne L9;
				L7:	getfield_a_this 15;		// reference thetapass/ThetaPassApplet.fs
					sload 6;
					sconst_4;
					sadd;
					aload_2;
					sload_3;
					sload 4;
					invokestatic 33;		// javacard/framework/Util.arrayCompare([BS[BSS)B
					ifne L9;
				L8:	sload 6;
					sreturn;
				L9:	sinc 8 1;
				L10:	sload 8;
					bspush 64;
					if_scmplt L2;
				L11:	sconst_m1;
					sreturn;
		}

		.method private searchRecordLocWithEName0AndType(B[BSS)S {
			.stack 5;
			.locals 4;

				L0:	sconst_0;
					sstore 8;
				L1:	goto L10;
				L2:	aload_0;
					sload 8;
					invokespecial 85;		// thetapass/ThetaPassApplet.getRecordLocOffset(S)S
					sstore 6;
				L3:	aload_0;
					getfield_a_this 15;		// reference thetapass/ThetaPassApplet.fs
					sload 6;
					sconst_0;
					sadd;
					baload;
					invokespecial 115;		// thetapass/ThetaPassApplet.getTypeFromFlag(B)B
					sstore 5;
				L4:	getfield_a_this 15;		// reference thetapass/ThetaPassApplet.fs
					sload 6;
					sconst_1;
					sadd;
					baload;
					sspush 255;
					sand;
					sstore 7;
				L5:	sload 5;
					sload_1;
					if_scmpne L9;
				L6:	sload 7;
					sload 4;
					if_scmpne L9;
				L7:	getfield_a_this 15;		// reference thetapass/ThetaPassApplet.fs
					sload 6;
					sconst_4;
					sadd;
					aload_2;
					sload_3;
					sload 4;
					invokestatic 33;		// javacard/framework/Util.arrayCompare([BS[BSS)B
					ifne L9;
				L8:	sload 8;
					sreturn;
				L9:	sinc 8 1;
				L10:	sload 8;
					bspush 64;
					if_scmplt L2;
				L11:	sconst_m1;
					sreturn;
		}

		.method private searchRecordLocOffsetWithTypeIndex(BS)S {
			.stack 4;
			.locals 4;

				L0:	sconst_0;
					sstore 5;
				L1:	sconst_0;
					sstore 6;
				L2:	goto L10;
				L3:	aload_0;
					sload 6;
					invokespecial 85;		// thetapass/ThetaPassApplet.getRecordLocOffset(S)S
					sstore 4;
				L4:	aload_0;
					getfield_a_this 15;		// reference thetapass/ThetaPassApplet.fs
					sload 4;
					sconst_0;
					sadd;
					baload;
					invokespecial 115;		// thetapass/ThetaPassApplet.getTypeFromFlag(B)B
					sstore_3;
				L5:	sload_3;
					sload_1;
					if_scmpne L9;
				L6:	sload_2;
					sload 5;
					if_scmpne L8;
				L7:	sload 4;
					sreturn;
				L8:	sinc 5 1;
				L9:	sinc 6 1;
				L10:	sload 6;
					bspush 64;
					if_scmplt L3;
				L11:	sconst_m1;
					sreturn;
		}

		.method private listRecordLocIndexWithType(B[BS)S {
			.stack 4;
			.locals 4;

				L0:	sconst_0;
					sstore 6;
				L1:	sconst_0;
					sstore 7;
				L2:	goto L8;
				L3:	aload_0;
					sload 7;
					invokespecial 85;		// thetapass/ThetaPassApplet.getRecordLocOffset(S)S
					sstore 5;
				L4:	aload_0;
					getfield_a_this 15;		// reference thetapass/ThetaPassApplet.fs
					sload 5;
					sconst_0;
					sadd;
					baload;
					invokespecial 115;		// thetapass/ThetaPassApplet.getTypeFromFlag(B)B
					sstore 4;
				L5:	sload 4;
					sload_1;
					if_scmpne L7;
				L6:	aload_2;
					sload_3;
					sload 6;
					sadd;
					sload 7;
					sspush 255;
					sand;
					s2b;
					bastore;
					sinc 6 1;
				L7:	sinc 7 1;
				L8:	sload 7;
					bspush 64;
					if_scmplt L3;
				L9:	sload 6;
					sreturn;
		}

		.method private getEName0FromLocOff(S[BS)S {
			.stack 5;
			.locals 1;

				L0:	getfield_a_this 15;		// reference thetapass/ThetaPassApplet.fs
					sload_1;
					sconst_1;
					sadd;
					baload;
					sspush 255;
					sand;
					sstore 4;
				L1:	getfield_a_this 15;		// reference thetapass/ThetaPassApplet.fs
					sload_1;
					sconst_4;
					sadd;
					aload_2;
					sload_3;
					sload 4;
					invokestatic 51;		// javacard/framework/Util.arrayCopyNonAtomic([BS[BSS)S
					pop;
					sload 4;
					sreturn;
		}

		.method private getEName1FromLocOff(S[BS)S {
			.stack 5;
			.locals 1;

				L0:	getfield_a_this 15;		// reference thetapass/ThetaPassApplet.fs
					sload_1;
					sconst_2;
					sadd;
					baload;
					sspush 255;
					sand;
					sstore 4;
				L1:	getfield_a_this 15;		// reference thetapass/ThetaPassApplet.fs
					sload_1;
					bspush 19;
					sadd;
					aload_2;
					sload_3;
					sload 4;
					invokestatic 51;		// javacard/framework/Util.arrayCopyNonAtomic([BS[BSS)S
					pop;
					sload 4;
					sreturn;
		}

		.method private getContentFromLocOff(S[BS)S {
			.stack 5;
			.locals 1;

				L0:	getfield_a_this 15;		// reference thetapass/ThetaPassApplet.fs
					sload_1;
					sconst_3;
					sadd;
					baload;
					sspush 255;
					sand;
					sstore 4;
				L1:	getfield_a_this 15;		// reference thetapass/ThetaPassApplet.fs
					sload_1;
					bspush 67;
					sadd;
					aload_2;
					sload_3;
					sload 4;
					invokestatic 51;		// javacard/framework/Util.arrayCopyNonAtomic([BS[BSS)S
					pop;
					sload 4;
					sreturn;
		}

		.method private getEmptyRecordLoc()S {
			.stack 4;
			.locals 2;

				L0:	sconst_0;
					sstore_2;
				L1:	goto L6;
				L2:	aload_0;
					sload_2;
					invokespecial 85;		// thetapass/ThetaPassApplet.getRecordLocOffset(S)S
					sstore_1;
				L3:	aload_0;
					getfield_a_this 15;		// reference thetapass/ThetaPassApplet.fs
					sload_1;
					sconst_0;
					sadd;
					baload;
					invokespecial 115;		// thetapass/ThetaPassApplet.getTypeFromFlag(B)B
					ifne L5;
				L4:	sload_2;
					sreturn;
				L5:	sinc 2 1;
				L6:	sload_2;
					bspush 64;
					if_scmplt L2;
				L7:	sconst_m1;
					sreturn;
		}

		.method private deleteRecord(B[BSS)Z {
			.stack 5;
			.locals 1;

				L0:	aload_0;
					sload_1;
					aload_2;
					sload_3;
					sload 4;
					invokespecial 116;		// thetapass/ThetaPassApplet.searchRecordLocOffsetWithEName0AndType(B[BSS)S
					sstore 5;
				L1:	sload 5;
					sconst_m1;
					if_scmpeq L3;
				L2:	invokestatic 117;		// javacard/framework/JCSystem.beginTransaction()V
					aload_0;
					sload 5;
					invokespecial 85;		// thetapass/ThetaPassApplet.getRecordLocOffset(S)S
					sstore 5;
					getfield_a_this 15;		// reference thetapass/ThetaPassApplet.fs
					sload 5;
					sspush 147;
					sconst_0;
					invokestatic 50;		// javacard/framework/Util.arrayFillNonAtomic([BSSB)S
					pop;
					invokestatic 118;		// javacard/framework/JCSystem.commitTransaction()V
					sconst_1;
					sreturn;
				L3:	sconst_0;
					sreturn;
		}

		.method private setRecord(B[BSS[BSS[BSS[BS)Z {
			.stack 7;
			.locals 2;

				L0:	sconst_m1;
					sstore 13;
				L1:	sconst_0;
					sstore 14;
				L2:	aload_0;
					sload_1;
					aload_2;
					sload_3;
					sload 4;
					invokespecial 111;		// thetapass/ThetaPassApplet.searchRecordLocWithEName0AndType(B[BSS)S
					sstore 13;
					sload 13;
					sconst_m1;
					if_scmpne L6;
				L3:	aload_0;
					invokespecial 119;		// thetapass/ThetaPassApplet.getEmptyRecordLoc()S
					sstore 13;
					sload 13;
					sconst_m1;
					if_scmpne L5;
				L4:	sconst_0;
					sreturn;
				L5:	getfield_a_this 15;		// reference thetapass/ThetaPassApplet.fs
					aload_0;
					sload 13;
					invokespecial 85;		// thetapass/ThetaPassApplet.getRecordLocOffset(S)S
					sconst_0;
					sadd;
					sload_1;
					bastore;
					sconst_1;
					sstore 14;
				L6:	aload_2;
					ifnull L10;
				L7:	sload 4;
					ifle L10;
				L8:	sload 14;
					ifeq L10;
				L9:	getfield_a_this 15;		// reference thetapass/ThetaPassApplet.fs
					aload_0;
					sload 13;
					invokespecial 85;		// thetapass/ThetaPassApplet.getRecordLocOffset(S)S
					sconst_1;
					sadd;
					sload 4;
					sspush 255;
					sand;
					s2b;
					bastore;
					getfield_a_this 15;		// reference thetapass/ThetaPassApplet.fs
					aload_0;
					sload 13;
					invokespecial 85;		// thetapass/ThetaPassApplet.getRecordLocOffset(S)S
					sconst_4;
					sadd;
					bspush 15;
					sconst_0;
					invokestatic 50;		// javacard/framework/Util.arrayFillNonAtomic([BSSB)S
					pop;
					aload_2;
					sload_3;
					getfield_a_this 15;		// reference thetapass/ThetaPassApplet.fs
					aload_0;
					sload 13;
					invokespecial 85;		// thetapass/ThetaPassApplet.getRecordLocOffset(S)S
					sconst_4;
					sadd;
					sload 4;
					invokestatic 120;		// javacard/framework/Util.arrayCopy([BS[BSS)S
					pop;
				L10:	aload 5;
					ifnull L13;
				L11:	sload 7;
					ifle L13;
				L12:	getfield_a_this 15;		// reference thetapass/ThetaPassApplet.fs
					aload_0;
					sload 13;
					invokespecial 85;		// thetapass/ThetaPassApplet.getRecordLocOffset(S)S
					sconst_2;
					sadd;
					sload 7;
					sspush 255;
					sand;
					s2b;
					bastore;
					getfield_a_this 15;		// reference thetapass/ThetaPassApplet.fs
					aload_0;
					sload 13;
					invokespecial 85;		// thetapass/ThetaPassApplet.getRecordLocOffset(S)S
					bspush 19;
					sadd;
					bspush 48;
					sconst_0;
					invokestatic 50;		// javacard/framework/Util.arrayFillNonAtomic([BSSB)S
					pop;
					aload 5;
					sload 6;
					getfield_a_this 15;		// reference thetapass/ThetaPassApplet.fs
					aload_0;
					sload 13;
					invokespecial 85;		// thetapass/ThetaPassApplet.getRecordLocOffset(S)S
					bspush 19;
					sadd;
					sload 7;
					invokestatic 120;		// javacard/framework/Util.arrayCopy([BS[BSS)S
					pop;
				L13:	aload 8;
					ifnull L17;
				L14:	sload 10;
					ifle L17;
				L15:	getfield_a_this 15;		// reference thetapass/ThetaPassApplet.fs
					aload_0;
					sload 13;
					invokespecial 85;		// thetapass/ThetaPassApplet.getRecordLocOffset(S)S
					sconst_3;
					sadd;
					sload 10;
					sspush 255;
					sand;
					s2b;
					bastore;
					getfield_a_this 15;		// reference thetapass/ThetaPassApplet.fs
					aload_0;
					sload 13;
					invokespecial 85;		// thetapass/ThetaPassApplet.getRecordLocOffset(S)S
					bspush 67;
					sadd;
					bspush 80;
					sconst_0;
					invokestatic 50;		// javacard/framework/Util.arrayFillNonAtomic([BSSB)S
					pop;
					aload_0;
					sconst_2;
					sload 13;
					aload 8;
					sload 9;
					aload 11;
					sload 12;
					invokespecial 88;		// thetapass/ThetaPassApplet.cryptoContent(BS[BS[BS)Z
					ifne L17;
				L16:	sconst_0;
					sreturn;
				L17:	sconst_1;
					sreturn;
		}

		.method private getRecordEName0List(BSS[BS)S {
			.stack 5;
			.locals 6;

				L0:	sconst_m1;
					sstore 6;
				L1:	sconst_m1;
					sstore 7;
				L2:	sconst_0;
					sstore 9;
				L3:	sload_3;
					bspush 6;
					if_scmpgt L17;
				L4:	sload_3;
					ifle L17;
				L5:	sconst_0;
					sstore 6;
					sconst_1;
					sstore 7;
					sconst_0;
					sstore 11;
				L6:	goto L15;
				L7:	aload_0;
					sload 11;
					invokespecial 85;		// thetapass/ThetaPassApplet.getRecordLocOffset(S)S
					sstore 8;
				L8:	aload_0;
					getfield_a_this 15;		// reference thetapass/ThetaPassApplet.fs
					sload 8;
					sconst_0;
					sadd;
					baload;
					invokespecial 115;		// thetapass/ThetaPassApplet.getTypeFromFlag(B)B
					ifne L14;
				L9:	sload 9;
					sload_2;
					if_scmplt L13;
				L10:	sload 6;
					sload_3;
					if_scmpge L13;
				L11:	aload_0;
					sload 8;
					aload 4;
					sload 7;
					sload 5;
					sadd;
					sconst_1;
					sadd;
					invokespecial 89;		// thetapass/ThetaPassApplet.getEName0FromLocOff(S[BS)S
					sstore 10;
				L12:	aload 4;
					sload 7;
					sload 5;
					sadd;
					sload 10;
					sspush 255;
					sand;
					s2b;
					bastore;
					sload 7;
					sload 10;
					sadd;
					sstore 7;
					sinc 6 1;
				L13:	sinc 9 1;
				L14:	sinc 11 1;
				L15:	sload 11;
					bspush 64;
					if_scmplt L7;
				L16:	aload 4;
					sload 5;
					sload 6;
					sspush 255;
					sand;
					s2b;
					bastore;
				L17:	sload 7;
					sreturn;
		}

		.method private cryptoContent(BS[BS[BS)Z {
			.stack 7;
			.locals 0;

				L0:	getfield_a_this 8;		// reference thetapass/ThetaPassApplet.md
					invokevirtual 91;		// reset()V
					getfield_a_this 8;		// reference thetapass/ThetaPassApplet.md
					getfield_a_this 16;		// reference thetapass/ThetaPassApplet.fsIV
					sconst_0;
					getfield_a_this 16;		// reference thetapass/ThetaPassApplet.fsIV
					arraylength;
					invokevirtual 92;		// update([BSS)V
					getfield_a_this 8;		// reference thetapass/ThetaPassApplet.md
					getfield_a_this 15;		// reference thetapass/ThetaPassApplet.fs
					sload_2;
					bspush 67;
					aload 5;
					sload 6;
					invokevirtual 93;		// doFinal([BSS[BS)S
					pop;
					sload_1;
					sconst_2;
					if_scmpne L2;
				L1:	getfield_a_this 6;		// reference thetapass/ThetaPassApplet.cipherNoPad
					getfield_a_this 18;		// reference thetapass/ThetaPassApplet.fsKey
					sload_1;
					aload 5;
					sload 6;
					bspush 16;
					invokevirtual 101;		// init(Ljavacard/security/Key;B[BSS)V
					getfield_a_this 6;		// reference thetapass/ThetaPassApplet.cipherNoPad
					aload_3;
					sload 4;
					bspush 80;
					getfield_a_this 15;		// reference thetapass/ThetaPassApplet.fs
					aload_0;
					sload_2;
					invokespecial 85;		// thetapass/ThetaPassApplet.getRecordLocOffset(S)S
					bspush 67;
					sadd;
					invokevirtual 102;		// doFinal([BSS[BS)S
					pop;
					sconst_1;
					sreturn;
				L2:	sload_1;
					sconst_1;
					if_scmpne L4;
				L3:	getfield_a_this 6;		// reference thetapass/ThetaPassApplet.cipherNoPad
					getfield_a_this 18;		// reference thetapass/ThetaPassApplet.fsKey
					sload_1;
					aload 5;
					sload 6;
					bspush 16;
					invokevirtual 101;		// init(Ljavacard/security/Key;B[BSS)V
					getfield_a_this 6;		// reference thetapass/ThetaPassApplet.cipherNoPad
					getfield_a_this 15;		// reference thetapass/ThetaPassApplet.fs
					aload_0;
					sload_2;
					invokespecial 85;		// thetapass/ThetaPassApplet.getRecordLocOffset(S)S
					bspush 67;
					sadd;
					bspush 80;
					aload_3;
					sload 4;
					invokevirtual 102;		// doFinal([BSS[BS)S
					pop;
					sconst_1;
					sreturn;
				L4:	sconst_0;
					sreturn;
		}

		.method public process(Ljavacard/framework/APDU;)V 7 {
			.stack 5;
			.locals 3;

			.descriptor	Ljavacard/framework/APDU;	1.10;

				L0:	aload_0;
					invokevirtual 121;		// selectingApplet()Z
					ifeq L2;
				L1:	return;
				L2:	aload_1;
					invokevirtual 122;		// getBuffer()[B
					astore_2;
				L3:	aload_2;
					sconst_1;
					baload;
					sstore_3;
				L4:	getstatic_a 54;		// reference thetapass/ThetaPassApplet.api
					ifnonnull L7;
				L5:	sload_3;
					ifeq L7;
				L6:	sspush 28447;
					invokestatic 68;		// javacard/framework/ISOException.throwIt(S)V
				L7:	sload_3;
					stableswitch L23 -2 16 L18 L22 L8 L10 L14 L15 L16 L23 L23 L23 L23 L23 L23 L23 L23 L23 L23 L23 L17;
				L8:	getstatic_a 54;		// reference thetapass/ThetaPassApplet.api
					ifnonnull_w L24;
				L9:	aload_0;
					aload_2;
					invokespecial 123;		// thetapass/ThetaPassApplet.initAPI([B)V
					goto L24;
				L10:	getfield_a_this 20;		// reference thetapass/ThetaPassApplet.pubKey
					invokeinterface 1 71 3;		// javacard/security/ECPublicKey
					ifeq L24;
				L11:	getfield_a_this 20;		// reference thetapass/ThetaPassApplet.pubKey
					aload_2;
					sconst_0;
					invokeinterface 3 71 19;		// javacard/security/ECPublicKey
					sstore 4;
				L12:	aload_1;
					sconst_0;
					sload 4;
					invokevirtual 107;		// setOutgoingAndSend(SS)V
				L13:	goto L24;
				L14:	getfield_a_this 15;		// reference thetapass/ThetaPassApplet.fs
					sconst_0;
					aload_2;
					sconst_0;
					sspush 256;
					invokestatic 51;		// javacard/framework/Util.arrayCopyNonAtomic([BS[BSS)S
					pop;
					aload_1;
					sconst_0;
					sspush 256;
					invokevirtual 107;		// setOutgoingAndSend(SS)V
					goto L24;
				L15:	aload_0;
					aload_1;
					aload_2;
					invokespecial 124;		// thetapass/ThetaPassApplet.fsGet(Ljavacard/framework/APDU;[B)V
					goto L24;
				L16:	aload_0;
					aload_1;
					aload_2;
					invokespecial 125;		// thetapass/ThetaPassApplet.fsPut(Ljavacard/framework/APDU;[B)V
					goto L24;
				L17:	aload_0;
					aload_1;
					aload_2;
					invokespecial 126;		// thetapass/ThetaPassApplet.mainMenu(Ljavacard/framework/APDU;[B)V
					goto L24;
				L18:	getfield_a_this 10;		// reference thetapass/ThetaPassApplet.sessKey
					invokeinterface 1 67 3;		// javacard/security/AESKey
					ifeq L24;
				L19:	getfield_a_this 10;		// reference thetapass/ThetaPassApplet.sessKey
					aload_2;
					sconst_0;
					invokeinterface 3 67 5;		// javacard/security/AESKey
					sstore 4;
				L20:	aload_1;
					sconst_0;
					sload 4;
					invokevirtual 107;		// setOutgoingAndSend(SS)V
				L21:	goto L24;
				L22:	aload_0;
					aload_1;
					aload_2;
					invokespecial 127;		// thetapass/ThetaPassApplet.secureChannel(Ljavacard/framework/APDU;[B)V
					goto L24;
				L23:	sspush 27904;
					invokestatic 68;		// javacard/framework/ISOException.throwIt(S)V
				L24:	return;
		}

	}

}
